# File: carstate.py.1shot.seq (Python 3.12)
# Disassembly generated by Pyarmor-Static-Unpack-1shot (v0.3.0), powered by pycdas

# ================================
# Pyarmor notes:
# - Pyarmor bytecode and code objects match standard Python, but special calls to Pyarmor runtime functions exist.
# - Calls on strings are not mistakes but markers, which are processed by Pyarmor at runtime.
#
# Decompilation guidance (without runtime):
# 1. Ignore encrypted bytes after `#`; use only the string before `#`.
# 2. Remove `"__pyarmor_enter_xxx__"(b"<COAddr>...")` and `"__pyarmor_leave_xxx__"(b"<COAddr>...")` (prologue/epilogue).
# 3. `"__pyarmor_assert_xxx__"(A)` is not a real assert statement.
#    - If `A` is a name or readable string: replace with `A`.
#    - If `A` is `(X, "Y")`: replace with `X.Y`.
#    - If `A` is `(X, "Y", Z)`: replace with `X.Y = Z`.
#    - Otherwise: choose the most reasonable replacement.
# 4. `"__pyarmor_bcc_xxx__"(...)` indicates native code; function body is not available. Add a comment.
# ================================

[Code]
    File Name: <frozen changan.carstate>
    Object Name: <module>
    Qualified Name: <module>
    Arg Count: 0
    Pos Only Arg Count: 0
    KW Only Arg Count: 0
    Stack Size: 5
    Flags: 0x20000000 (CO_PYARMOR_OBFUSCATED)
    [Names]
        '__assert_armored__'
        'copy'
        'time'
        'opendbc.car.common.conversions'
        'Conversions'
        'CV'
        'openpilot.common.filter_simple'
        'FirstOrderFilter'
        'openpilot.common.realtime'
        'DT_CTRL'
        'opendbc.can'
        'CANDefine'
        'CANParser'
        'opendbc.car.interfaces'
        'CarStateBase'
        'opendbc.car.changan.values'
        'CAR'
        'DBC'
        'STEER_THRESHOLD'
        'EPS_SCALE'
        'opendbc.car'
        'Bus'
        'structs'
        'CarParams'
        'SteerControlType'
        'TEMP_STEER_FAULTS'
        'PERM_STEER_FAULTS'
        'CarState'
    [Locals+Names]
    [Constants]
        '__pyarmor_assert_41364__'
        '__pyarmor_enter_41365__'
        b'<COAddr>\x03\x00\x00\x1a\xd6\x00\x00\x00\x00\x00\x00\x00'
        0
        None
        (
            'Conversions'
        )
        (
            'FirstOrderFilter'
        )
        (
            'DT_CTRL'
        )
        (
            'CANDefine'
            'CANParser'
        )
        (
            'CarStateBase'
        )
        (
            'CAR'
            'DBC'
            'STEER_THRESHOLD'
            'EPS_SCALE'
        )
        (
            'Bus'
            'structs'
        )
        (
            0
            9
            11
            21
            25
        )
        (
            3
            17
        )
        [Code]
            File Name: <frozen changan.carstate>
            Object Name: CarState
            Qualified Name: CarState
            Arg Count: 0
            Pos Only Arg Count: 0
            KW Only Arg Count: 0
            Stack Size: 5
            Flags: 0x20000000 (CO_PYARMOR_OBFUSCATED)
            [Names]
                '__name__'
                '__module__'
                '__qualname__'
                '__assert_armored__'
                '__init__'
                'structs'
                'CarState'
                'update'
                'staticmethod'
                'get_can_parsers'
                '__classcell__'
            [Locals+Names]
                '__class__'
            [Constants]
                'CarState'
                '__pyarmor_assert_41367__'
                '__pyarmor_enter_41368__'
                b'<COAddr>\x03\x00\x00$V\x00\x00\x00\x00\x00\x00\x00'
                [Code]
                    File Name: <frozen changan.carstate>
                    Object Name: __init__
                    Qualified Name: CarState.__init__
                    Arg Count: 2
                    Pos Only Arg Count: 0
                    KW Only Arg Count: 0
                    Stack Size: 6
                    Flags: 0x20000003 (CO_OPTIMIZED | CO_NEWLOCALS | CO_PYARMOR_OBFUSCATED)
                    [Names]
                        'super'
                        '__init__'
                        'CANDefine'
                        'DBC'
                        'carFingerprint'
                        'Bus'
                        'pt'
                        'CAR'
                        'QIYUAN_A05'
                        'dv'
                        'shifter_values'
                        'EPS_SCALE'
                        'eps_torque_scale'
                        'CV'
                        'KPH_TO_MS'
                        'cluster_speed_hyst_gap'
                        'cluster_min_speed'
                        'FirstOrderFilter'
                        'DT_CTRL'
                        'angle_offset'
                        'prev_distance_button'
                        'distance_button'
                        'pcm_follow_distance'
                        'low_speed_lockout'
                        'acc_type'
                        'lkas_hud'
                        'cruiseEnable'
                        'time'
                        'cruiseTiming'
                        'cruiseEnablePrev'
                        'cruiseSpeed'
                        'buttonPlus'
                        'buttonReduce'
                        'counter_244'
                        'counter_1ba'
                        'counter_17e'
                        'counter_307'
                        'counter_31a'
                        'sigs244'
                        'sigs1ba'
                        'sigs17e'
                        'sigs307'
                        'sigs31a'
                        'steeringPressed'
                        'steeringPressedMax'
                        'steeringPressedMin'
                        'iacc_enable_switch_button_pressed'
                        'iacc_enable_switch_button_prev'
                        'iacc_enable_switch_button_rising_edge'
                    [Locals+Names]
                        'self'
                        'CP'
                        '__assert_armored__'
                        '_var_var_0'
                        '__class__'
                    [Constants]
                        None
                        '__pyarmor_assert_41370__'
                        '__pyarmor_enter_41371__'
                        b'<COAddr>\x01\x00\x00\x1c\x98\x03\x00\x00\x00\x00\x00\x00'
                        'GW_331'
                        'TCU_GearForDisplay'
                        'GW_338'
                        100
                        2
                        60
                        False
                        (
                            'initialized'
                        )
                        0
                        1
                        '__pyarmor_exit_41372__'
                    [Disassembly]
                        0       COPY_FREE_VARS                  1
                        2       NOP                             
                        4       NOP                             
                        6       PUSH_NULL                       
                        8       LOAD_CONST                      2: '__pyarmor_enter_41371__'
                        10      LOAD_CONST                      3: b'<COAddr>\x01\x00\x00\x1c\x98\x03\x00\x00\x00\x00\x00\x00'
                        12      BUILD_TUPLE                     1
                        14      CALL_FUNCTION_EX                0
                        16      POP_TOP                         
                        18      RESUME                          0
                        20      NOP                             
                        22      NOP                             
                        24      NOP                             
                        26      NOP                             
                        28      NOP                             
                        30      LOAD_GLOBAL                     0: super
                        40      LOAD_DEREF                      4: __class__
                        42      LOAD_FAST                       0: self
                        44      LOAD_SUPER_ATTR                 5: __init__
                        48      LOAD_FAST                       1: CP
                        50      CALL                            1
                        58      POP_TOP                         
                        60      LOAD_GLOBAL                     5: NULL + CANDefine
                        70      LOAD_GLOBAL                     6: DBC
                        80      LOAD_FAST                       1: CP
                        82      LOAD_ATTR                       8: carFingerprint
                        102     BINARY_SUBSCR                   
                        106     LOAD_GLOBAL                     10: Bus
                        116     LOAD_ATTR                       12: pt
                        136     BINARY_SUBSCR                   
                        140     CALL                            1
                        148     STORE_FAST                      3: _var_var_0
                        150     LOAD_FAST                       1: CP
                        152     LOAD_ATTR                       8: carFingerprint
                        172     LOAD_GLOBAL                     14: CAR
                        182     LOAD_ATTR                       16: QIYUAN_A05
                        202     COMPARE_OP                      40 (==)
                        206     POP_JUMP_IF_FALSE               24 (to 256)
                        208     LOAD_FAST                       3: _var_var_0
                        210     LOAD_ATTR                       18: dv
                        230     LOAD_CONST                      4: 'GW_331'
                        232     BINARY_SUBSCR                   
                        236     LOAD_CONST                      5: 'TCU_GearForDisplay'
                        238     BINARY_SUBSCR                   
                        242     LOAD_FAST                       0: self
                        244     STORE_ATTR                      10: shifter_values
                        254     JUMP_FORWARD                    23 (to 302)
                        256     LOAD_FAST                       3: _var_var_0
                        258     LOAD_ATTR                       18: dv
                        278     LOAD_CONST                      6: 'GW_338'
                        280     BINARY_SUBSCR                   
                        284     LOAD_CONST                      5: 'TCU_GearForDisplay'
                        286     BINARY_SUBSCR                   
                        290     LOAD_FAST                       0: self
                        292     STORE_ATTR                      10: shifter_values
                        302     LOAD_GLOBAL                     22: EPS_SCALE
                        312     LOAD_FAST                       1: CP
                        314     LOAD_ATTR                       8: carFingerprint
                        334     BINARY_SUBSCR                   
                        338     LOAD_CONST                      7: 100
                        340     BINARY_OP                       11 (/)
                        344     LOAD_FAST                       0: self
                        346     STORE_ATTR                      12: eps_torque_scale
                        356     LOAD_GLOBAL                     26: CV
                        366     LOAD_ATTR                       28: KPH_TO_MS
                        386     LOAD_CONST                      8: 2
                        388     BINARY_OP                       11 (/)
                        392     LOAD_FAST                       0: self
                        394     STORE_ATTR                      15: cluster_speed_hyst_gap
                        404     LOAD_GLOBAL                     26: CV
                        414     LOAD_ATTR                       28: KPH_TO_MS
                        434     LOAD_CONST                      8: 2
                        436     BINARY_OP                       11 (/)
                        440     LOAD_FAST                       0: self
                        442     STORE_ATTR                      16: cluster_min_speed
                        452     LOAD_GLOBAL                     35: NULL + FirstOrderFilter
                        462     LOAD_CONST                      0: None
                        464     LOAD_CONST                      9: 60
                        466     LOAD_GLOBAL                     36: DT_CTRL
                        476     LOAD_CONST                      10: False
                        478     KW_NAMES                        11: ('initialized',)
                        480     CALL                            4
                        488     LOAD_FAST                       0: self
                        490     STORE_ATTR                      19: angle_offset
                        500     LOAD_CONST                      12: 0
                        502     LOAD_FAST                       0: self
                        504     STORE_ATTR                      20: prev_distance_button
                        514     LOAD_CONST                      12: 0
                        516     LOAD_FAST                       0: self
                        518     STORE_ATTR                      21: distance_button
                        528     LOAD_CONST                      12: 0
                        530     LOAD_FAST                       0: self
                        532     STORE_ATTR                      22: pcm_follow_distance
                        542     LOAD_CONST                      10: False
                        544     LOAD_FAST                       0: self
                        546     STORE_ATTR                      23: low_speed_lockout
                        556     LOAD_CONST                      13: 1
                        558     LOAD_FAST                       0: self
                        560     STORE_ATTR                      24: acc_type
                        570     BUILD_MAP                       0
                        572     LOAD_FAST                       0: self
                        574     STORE_ATTR                      25: lkas_hud
                        584     LOAD_CONST                      10: False
                        586     LOAD_FAST                       0: self
                        588     STORE_ATTR                      26: cruiseEnable
                        598     LOAD_GLOBAL                     55: NULL + time
                        608     LOAD_ATTR                       54: time
                        628     CALL                            0
                        636     LOAD_FAST                       0: self
                        638     STORE_ATTR                      28: cruiseTiming
                        648     LOAD_CONST                      10: False
                        650     LOAD_FAST                       0: self
                        652     STORE_ATTR                      29: cruiseEnablePrev
                        662     LOAD_CONST                      12: 0
                        664     LOAD_FAST                       0: self
                        666     STORE_ATTR                      30: cruiseSpeed
                        676     LOAD_CONST                      12: 0
                        678     LOAD_FAST                       0: self
                        680     STORE_ATTR                      31: buttonPlus
                        690     LOAD_CONST                      12: 0
                        692     LOAD_FAST                       0: self
                        694     STORE_ATTR                      32: buttonReduce
                        704     LOAD_CONST                      12: 0
                        706     LOAD_FAST                       0: self
                        708     STORE_ATTR                      33: counter_244
                        718     LOAD_CONST                      12: 0
                        720     LOAD_FAST                       0: self
                        722     STORE_ATTR                      34: counter_1ba
                        732     LOAD_CONST                      12: 0
                        734     LOAD_FAST                       0: self
                        736     STORE_ATTR                      35: counter_17e
                        746     LOAD_CONST                      12: 0
                        748     LOAD_FAST                       0: self
                        750     STORE_ATTR                      36: counter_307
                        760     LOAD_CONST                      12: 0
                        762     LOAD_FAST                       0: self
                        764     STORE_ATTR                      37: counter_31a
                        774     LOAD_CONST                      12: 0
                        776     LOAD_FAST                       0: self
                        778     STORE_ATTR                      38: sigs244
                        788     LOAD_CONST                      12: 0
                        790     LOAD_FAST                       0: self
                        792     STORE_ATTR                      39: sigs1ba
                        802     LOAD_CONST                      12: 0
                        804     LOAD_FAST                       0: self
                        806     STORE_ATTR                      40: sigs17e
                        816     LOAD_CONST                      12: 0
                        818     LOAD_FAST                       0: self
                        820     STORE_ATTR                      41: sigs307
                        830     LOAD_CONST                      12: 0
                        832     LOAD_FAST                       0: self
                        834     STORE_ATTR                      42: sigs31a
                        844     LOAD_CONST                      10: False
                        846     LOAD_FAST                       0: self
                        848     STORE_ATTR                      43: steeringPressed
                        858     LOAD_CONST                      12: 0
                        860     LOAD_FAST                       0: self
                        862     STORE_ATTR                      44: steeringPressedMax
                        872     LOAD_CONST                      12: 0
                        874     LOAD_FAST                       0: self
                        876     STORE_ATTR                      45: steeringPressedMin
                        886     LOAD_CONST                      12: 0
                        888     LOAD_FAST                       0: self
                        890     STORE_ATTR                      46: iacc_enable_switch_button_pressed
                        900     LOAD_CONST                      12: 0
                        902     LOAD_FAST                       0: self
                        904     STORE_ATTR                      47: iacc_enable_switch_button_prev
                        914     LOAD_CONST                      10: False
                        916     LOAD_FAST                       0: self
                        918     STORE_ATTR                      48: iacc_enable_switch_button_rising_edge
                        928     LOAD_CONST                      0: None
                        930     NOP                             
                        932     NOP                             
                        934     NOP                             
                        936     JUMP_FORWARD                    19 (to 976)
                        944     POP_TOP                         
                        946     RETURN_CONST                    0: None
                        948     PUSH_EXC_INFO                   
                        950     PUSH_NULL                       
                        952     LOAD_CONST                      14: '__pyarmor_exit_41372__'
                        954     NOP                             
                        956     LOAD_CONST                      3: b'<COAddr>\x01\x00\x00\x1c\x98\x03\x00\x00\x00\x00\x00\x00'
                        958     CALL                            1
                        966     POP_TOP                         
                        968     RERAISE                         0
                        970     COPY                            3
                        972     POP_EXCEPT                      
                        974     RERAISE                         1
                        976     PUSH_NULL                       
                        978     LOAD_CONST                      14: '__pyarmor_exit_41372__'
                        980     LOAD_CONST                      3: b'<COAddr>\x01\x00\x00\x1c\x98\x03\x00\x00\x00\x00\x00\x00'
                        982     BUILD_TUPLE                     1
                        984     CALL_FUNCTION_EX                0
                        986     POP_TOP                         
                        988     RETURN_VALUE                    
                    [Exception Table]
                        30 to 928 -> 948 [0] 
                        948 to 970 -> 970 [1] lasti
                'return'
                [Code]
                    File Name: <frozen changan.carstate>
                    Object Name: update
                    Qualified Name: CarState.update
                    Arg Count: 2
                    Pos Only Arg Count: 0
                    KW Only Arg Count: 0
                    Stack Size: 6
                    Flags: 0x20000003 (CO_OPTIMIZED | CO_NEWLOCALS | CO_PYARMOR_OBFUSCATED)
                    [Names]
                        'Bus'
                        'pt'
                        'cam'
                        'structs'
                        'CarState'
                        'any'
                        'vl'
                        'doorOpen'
                        'seatbeltUnlatched'
                        'parkingBrake'
                        'CP'
                        'carFingerprint'
                        'CAR'
                        'CHANGAN_Z6_IDD'
                        'QIYUAN_A07'
                        'CV'
                        'KPH_TO_MS'
                        'vEgoRaw'
                        'update_speed_kf'
                        'vEgo'
                        'aEgo'
                        'vEgoCluster'
                        'abs'
                        'standstill'
                        'steeringAngleOffsetDeg'
                        'steeringAngleDeg'
                        'steeringRateDeg'
                        'QIYUAN_A05'
                        'int'
                        'brakePressed'
                        'gasPressed'
                        'steeringPressedMax'
                        'steeringPressedMin'
                        'leftBlindspot'
                        'rightBlindspot'
                        'GearShifter'
                        'drive'
                        'gearShifter'
                        'parse_gear_shifter'
                        'shifter_values'
                        'get'
                        'update_blinker_from_stalk'
                        'leftBlinker'
                        'rightBlinker'
                        'steeringTorque'
                        'steeringTorqueEps'
                        'steeringPressed'
                        'steerFaultTemporary'
                        'cruiseEnable'
                        'iacc_enable_switch_button_pressed'
                        'iacc_enable_switch_button_prev'
                        'iacc_enable_switch_button_rising_edge'
                        'cruiseEnablePrev'
                        'cruiseSpeed'
                        'buttonPlus'
                        'buttonReduce'
                        'max'
                        'accFaulted'
                        'cruiseState'
                        'available'
                        'speed'
                        'speedCluster'
                        'stockFcw'
                        'enabled'
                        'genericToggle'
                        'stockAeb'
                        'copy'
                        'sigs244'
                        'sigs1ba'
                        'sigs17e'
                        'sigs307'
                        'sigs31a'
                        'counter_244'
                        'counter_1ba'
                        'counter_17e'
                        'counter_307'
                        'counter_31a'
                        'distance_button'
                        'prev_distance_button'
                    [Locals+Names]
                        'self'
                        'can_parsers'
                        '__assert_armored__'
                        '_var_var_1'
                        '_var_var_2'
                        '_var_var_3'
                        '_var_var_4'
                        '_var_var_5'
                        '_var_var_6'
                        '_var_var_7'
                    [Constants]
                        None
                        '__pyarmor_assert_41373__'
                        '__pyarmor_enter_41374__'
                        b'<COAddr>\x01\x00\x00\x1a\xee\x14\x00\x00\x00\x00\x00\x00'
                        'GW_28B'
                        'BCM_DriverDoorStatus'
                        'GW_50'
                        'SRS_DriverBuckleSwitchStatus'
                        1
                        False
                        'GW_17A'
                        'ESP_VehicleSpeed'
                        'GW_1C2'
                        'GW_187'
                        5
                        0.98
                        2
                        0.001
                        0
                        'GW_180'
                        'SAS_SteeringAngle'
                        'SAS_SteeringAngleSpeed'
                        'GW_331'
                        'TCU_GearForDisplay'
                        'GW_17D'
                        'PCU_BrkPedlSts'
                        'PCU_RealAccPedl'
                        1.5
                        0.5
                        'GW_2A4'
                        'LCDAR_Left_BSD_LCAAlert'
                        'LCDAR_BSD_LCAAlert'
                        'GW_161'
                        'EMS_RealAccPedal'
                        'GW_338'
                        'GW_1A6'
                        'EMS_BrakePedalStatus'
                        'GW_1C6'
                        3
                        'GW_196'
                        6
                        200
                        'BCM_TurnIndicatorLeft'
                        'BCM_TurnIndicatorRight'
                        'GW_17E'
                        'EPS_MeasuredTorsionBarTorque'
                        'GW_170'
                        'EPS_ActualTorsionBarTorq'
                        90
                        True
                        'GW_24F'
                        'EPS_EPSFailed'
                        'EPS_LatCtrlAvailabilityStatus'
                        'GW_28C'
                        'GW_MFS_IACCenable_switch_signal'
                        'GW_MFS_Cancle_switch_signal'
                        'GW_MFS_RESPlus_switch_signal'
                        'GW_MFS_SETReduce_switch_signal'
                        'GW_244'
                        'ACC_ACCMode'
                        7
                        'GW_31A'
                        'ACC_IACCHWAMode'
                        'ACC_IACCHWAEnable'
                        'ACC_FCWPreWarning'
                        'ACC_AEBCtrlType'
                        'GW_1BA'
                        'GW_307'
                        'ACC_RollingCounter_24E'
                        'ACC_RollingCounter_1BA'
                        'EPS_RollingCounter_17E'
                        'ACC_RollingCounter_35E'
                        'ACC_RollingCounter_36D'
                        'ACC_DistanceLevel'
                        '__pyarmor_exit_41375__'
                    [Disassembly]
                        0       NOP                             
                        2       NOP                             
                        4       PUSH_NULL                       
                        6       LOAD_CONST                      2: '__pyarmor_enter_41374__'
                        8       LOAD_CONST                      3: b'<COAddr>\x01\x00\x00\x1a\xee\x14\x00\x00\x00\x00\x00\x00'
                        10      BUILD_TUPLE                     1
                        12      CALL_FUNCTION_EX                0
                        14      POP_TOP                         
                        16      RESUME                          0
                        18      NOP                             
                        20      NOP                             
                        22      NOP                             
                        24      NOP                             
                        26      NOP                             
                        28      LOAD_FAST                       1: can_parsers
                        30      LOAD_GLOBAL                     0: Bus
                        40      LOAD_ATTR                       2: pt
                        60      BINARY_SUBSCR                   
                        64      STORE_FAST                      3: _var_var_1
                        66      LOAD_FAST                       1: can_parsers
                        68      LOAD_GLOBAL                     0: Bus
                        78      LOAD_ATTR                       4: cam
                        98      BINARY_SUBSCR                   
                        102     STORE_FAST                      4: _var_var_2
                        104     LOAD_GLOBAL                     7: NULL + structs
                        114     LOAD_ATTR                       8: CarState
                        134     CALL                            0
                        142     STORE_FAST                      5: _var_var_3
                        144     LOAD_GLOBAL                     11: NULL + any
                        154     LOAD_FAST                       3: _var_var_1
                        156     LOAD_ATTR                       12: vl
                        176     LOAD_CONST                      4: 'GW_28B'
                        178     BINARY_SUBSCR                   
                        182     LOAD_CONST                      5: 'BCM_DriverDoorStatus'
                        184     BINARY_SUBSCR                   
                        188     BUILD_LIST                      1
                        190     CALL                            1
                        198     LOAD_FAST                       5: _var_var_3
                        200     STORE_ATTR                      7: doorOpen
                        210     LOAD_FAST                       3: _var_var_1
                        212     LOAD_ATTR                       12: vl
                        232     LOAD_CONST                      6: 'GW_50'
                        234     BINARY_SUBSCR                   
                        238     LOAD_CONST                      7: 'SRS_DriverBuckleSwitchStatus'
                        240     BINARY_SUBSCR                   
                        244     LOAD_CONST                      8: 1
                        246     COMPARE_OP                      40 (==)
                        250     LOAD_FAST                       5: _var_var_3
                        252     STORE_ATTR                      8: seatbeltUnlatched
                        262     LOAD_CONST                      9: False
                        264     LOAD_FAST                       5: _var_var_3
                        266     STORE_ATTR                      9: parkingBrake
                        276     LOAD_FAST                       0: self
                        278     LOAD_ATTR                       20: CP
                        298     LOAD_ATTR                       22: carFingerprint
                        318     LOAD_GLOBAL                     24: CAR
                        328     LOAD_ATTR                       26: CHANGAN_Z6_IDD
                        348     COMPARE_OP                      40 (==)
                        352     POP_JUMP_IF_FALSE               19 (to 392)
                        354     LOAD_FAST                       3: _var_var_1
                        356     LOAD_ATTR                       12: vl
                        376     LOAD_CONST                      10: 'GW_17A'
                        378     BINARY_SUBSCR                   
                        382     LOAD_CONST                      11: 'ESP_VehicleSpeed'
                        384     BINARY_SUBSCR                   
                        388     STORE_FAST                      6: _var_var_4
                        390     JUMP_FORWARD                    76 (to 544)
                        392     LOAD_FAST                       0: self
                        394     LOAD_ATTR                       20: CP
                        414     LOAD_ATTR                       22: carFingerprint
                        434     LOAD_GLOBAL                     24: CAR
                        444     LOAD_ATTR                       28: QIYUAN_A07
                        464     COMPARE_OP                      40 (==)
                        468     POP_JUMP_IF_FALSE               19 (to 508)
                        470     LOAD_FAST                       3: _var_var_1
                        472     LOAD_ATTR                       12: vl
                        492     LOAD_CONST                      12: 'GW_1C2'
                        494     BINARY_SUBSCR                   
                        498     LOAD_CONST                      11: 'ESP_VehicleSpeed'
                        500     BINARY_SUBSCR                   
                        504     STORE_FAST                      6: _var_var_4
                        506     JUMP_FORWARD                    18 (to 544)
                        508     LOAD_FAST                       3: _var_var_1
                        510     LOAD_ATTR                       12: vl
                        530     LOAD_CONST                      13: 'GW_187'
                        532     BINARY_SUBSCR                   
                        536     LOAD_CONST                      11: 'ESP_VehicleSpeed'
                        538     BINARY_SUBSCR                   
                        542     STORE_FAST                      6: _var_var_4
                        544     LOAD_FAST                       6: _var_var_4
                        546     LOAD_CONST                      14: 5
                        548     COMPARE_OP                      26 (<=)
                        552     POP_JUMP_IF_FALSE               2 (to 558)
                        554     LOAD_FAST                       6: _var_var_4
                        556     JUMP_FORWARD                    7 (to 572)
                        558     LOAD_FAST                       6: _var_var_4
                        560     LOAD_CONST                      15: 0.98
                        562     BINARY_OP                       11 (/)
                        566     LOAD_CONST                      16: 2
                        568     BINARY_OP                       0 (+)
                        572     STORE_FAST                      7: _var_var_5
                        574     LOAD_FAST                       7: _var_var_5
                        576     LOAD_GLOBAL                     30: CV
                        586     LOAD_ATTR                       32: KPH_TO_MS
                        606     BINARY_OP                       5 (*)
                        610     LOAD_FAST                       5: _var_var_3
                        612     STORE_ATTR                      17: vEgoRaw
                        622     LOAD_FAST                       0: self
                        624     LOAD_ATTR                       37: update_speed_kf
                        644     LOAD_FAST                       5: _var_var_3
                        646     LOAD_ATTR                       34: vEgoRaw
                        666     CALL                            1
                        674     UNPACK_SEQUENCE                 2
                        678     LOAD_FAST                       5: _var_var_3
                        680     STORE_ATTR                      19: vEgo
                        690     LOAD_FAST                       5: _var_var_3
                        692     STORE_ATTR                      20: aEgo
                        702     LOAD_FAST                       5: _var_var_3
                        704     LOAD_ATTR                       38: vEgo
                        724     LOAD_FAST                       5: _var_var_3
                        726     STORE_ATTR                      21: vEgoCluster
                        736     LOAD_GLOBAL                     45: NULL + abs
                        746     LOAD_FAST                       5: _var_var_3
                        748     LOAD_ATTR                       34: vEgoRaw
                        768     CALL                            1
                        776     LOAD_CONST                      17: 0.001
                        778     COMPARE_OP                      2 (<)
                        782     LOAD_FAST                       5: _var_var_3
                        784     STORE_ATTR                      23: standstill
                        794     LOAD_CONST                      18: 0
                        796     LOAD_FAST                       5: _var_var_3
                        798     STORE_ATTR                      24: steeringAngleOffsetDeg
                        808     LOAD_FAST                       3: _var_var_1
                        810     LOAD_ATTR                       12: vl
                        830     LOAD_CONST                      19: 'GW_180'
                        832     BINARY_SUBSCR                   
                        836     LOAD_CONST                      20: 'SAS_SteeringAngle'
                        838     BINARY_SUBSCR                   
                        842     LOAD_FAST                       5: _var_var_3
                        844     STORE_ATTR                      25: steeringAngleDeg
                        854     LOAD_FAST                       3: _var_var_1
                        856     LOAD_ATTR                       12: vl
                        876     LOAD_CONST                      19: 'GW_180'
                        878     BINARY_SUBSCR                   
                        882     LOAD_CONST                      21: 'SAS_SteeringAngleSpeed'
                        884     BINARY_SUBSCR                   
                        888     LOAD_FAST                       5: _var_var_3
                        890     STORE_ATTR                      26: steeringRateDeg
                        900     LOAD_FAST                       0: self
                        902     LOAD_ATTR                       20: CP
                        922     LOAD_ATTR                       22: carFingerprint
                        942     LOAD_GLOBAL                     24: CAR
                        952     LOAD_ATTR                       54: QIYUAN_A05
                        972     COMPARE_OP                      40 (==)
                        976     POP_JUMP_IF_FALSE               193 (to 1364)
                        978     LOAD_GLOBAL                     57: NULL + int
                        988     LOAD_FAST                       3: _var_var_1
                        990     LOAD_ATTR                       12: vl
                        1010    LOAD_CONST                      22: 'GW_331'
                        1012    BINARY_SUBSCR                   
                        1016    LOAD_CONST                      23: 'TCU_GearForDisplay'
                        1018    BINARY_SUBSCR                   
                        1022    CALL                            1
                        1030    STORE_FAST                      8: _var_var_6
                        1032    LOAD_FAST                       3: _var_var_1
                        1034    LOAD_ATTR                       12: vl
                        1054    LOAD_CONST                      24: 'GW_17D'
                        1056    BINARY_SUBSCR                   
                        1060    LOAD_CONST                      25: 'PCU_BrkPedlSts'
                        1062    BINARY_SUBSCR                   
                        1066    LOAD_CONST                      18: 0
                        1068    COMPARE_OP                      55 (!=)
                        1072    LOAD_FAST                       5: _var_var_3
                        1074    STORE_ATTR                      29: brakePressed
                        1084    LOAD_FAST                       3: _var_var_1
                        1086    LOAD_ATTR                       12: vl
                        1106    LOAD_CONST                      24: 'GW_17D'
                        1108    BINARY_SUBSCR                   
                        1112    LOAD_CONST                      26: 'PCU_RealAccPedl'
                        1114    BINARY_SUBSCR                   
                        1118    LOAD_CONST                      18: 0
                        1120    COMPARE_OP                      55 (!=)
                        1124    LOAD_FAST                       5: _var_var_3
                        1126    STORE_ATTR                      30: gasPressed
                        1136    LOAD_CONST                      27: 1.5
                        1138    LOAD_FAST                       0: self
                        1140    STORE_ATTR                      31: steeringPressedMax
                        1150    LOAD_CONST                      28: 0.5
                        1152    LOAD_FAST                       0: self
                        1154    STORE_ATTR                      32: steeringPressedMin
                        1164    LOAD_FAST                       3: _var_var_1
                        1166    LOAD_ATTR                       12: vl
                        1186    LOAD_CONST                      29: 'GW_2A4'
                        1188    BINARY_SUBSCR                   
                        1192    LOAD_CONST                      30: 'LCDAR_Left_BSD_LCAAlert'
                        1194    BINARY_SUBSCR                   
                        1198    LOAD_CONST                      8: 1
                        1200    COMPARE_OP                      40 (==)
                        1204    COPY                            1
                        1206    POP_JUMP_IF_TRUE                21 (to 1250)
                        1208    POP_TOP                         
                        1210    LOAD_FAST                       3: _var_var_1
                        1212    LOAD_ATTR                       12: vl
                        1232    LOAD_CONST                      29: 'GW_2A4'
                        1234    BINARY_SUBSCR                   
                        1238    LOAD_CONST                      30: 'LCDAR_Left_BSD_LCAAlert'
                        1240    BINARY_SUBSCR                   
                        1244    LOAD_CONST                      16: 2
                        1246    COMPARE_OP                      40 (==)
                        1250    LOAD_FAST                       5: _var_var_3
                        1252    STORE_ATTR                      33: leftBlindspot
                        1262    LOAD_FAST                       3: _var_var_1
                        1264    LOAD_ATTR                       12: vl
                        1284    LOAD_CONST                      29: 'GW_2A4'
                        1286    BINARY_SUBSCR                   
                        1290    LOAD_CONST                      31: 'LCDAR_BSD_LCAAlert'
                        1292    BINARY_SUBSCR                   
                        1296    LOAD_CONST                      8: 1
                        1298    COMPARE_OP                      40 (==)
                        1302    COPY                            1
                        1304    POP_JUMP_IF_TRUE                21 (to 1348)
                        1306    POP_TOP                         
                        1308    LOAD_FAST                       3: _var_var_1
                        1310    LOAD_ATTR                       12: vl
                        1330    LOAD_CONST                      29: 'GW_2A4'
                        1332    BINARY_SUBSCR                   
                        1336    LOAD_CONST                      31: 'LCDAR_BSD_LCAAlert'
                        1338    BINARY_SUBSCR                   
                        1342    LOAD_CONST                      16: 2
                        1344    COMPARE_OP                      40 (==)
                        1348    LOAD_FAST                       5: _var_var_3
                        1350    STORE_ATTR                      34: rightBlindspot
                        1360    JUMP_FORWARD                    355 (to 2074)
                        1364    LOAD_FAST                       0: self
                        1366    LOAD_ATTR                       20: CP
                        1386    LOAD_ATTR                       22: carFingerprint
                        1406    LOAD_GLOBAL                     24: CAR
                        1416    LOAD_ATTR                       28: QIYUAN_A07
                        1436    COMPARE_OP                      40 (==)
                        1440    POP_JUMP_IF_FALSE               62 (to 1566)
                        1442    LOAD_CONST                      9: False
                        1444    LOAD_FAST                       5: _var_var_3
                        1446    STORE_ATTR                      29: brakePressed
                        1456    LOAD_FAST                       3: _var_var_1
                        1458    LOAD_ATTR                       12: vl
                        1478    LOAD_CONST                      32: 'GW_161'
                        1480    BINARY_SUBSCR                   
                        1484    LOAD_CONST                      33: 'EMS_RealAccPedal'
                        1486    BINARY_SUBSCR                   
                        1490    LOAD_CONST                      18: 0
                        1492    COMPARE_OP                      55 (!=)
                        1496    LOAD_FAST                       5: _var_var_3
                        1498    STORE_ATTR                      30: gasPressed
                        1508    LOAD_CONST                      27: 1.5
                        1510    LOAD_FAST                       0: self
                        1512    STORE_ATTR                      31: steeringPressedMax
                        1522    LOAD_CONST                      28: 0.5
                        1524    LOAD_FAST                       0: self
                        1526    STORE_ATTR                      32: steeringPressedMin
                        1536    LOAD_CONST                      9: False
                        1538    LOAD_FAST                       5: _var_var_3
                        1540    STORE_ATTR                      33: leftBlindspot
                        1550    LOAD_CONST                      9: False
                        1552    LOAD_FAST                       5: _var_var_3
                        1554    STORE_ATTR                      34: rightBlindspot
                        1564    JUMP_FORWARD                    254 (to 2074)
                        1566    LOAD_FAST                       0: self
                        1568    LOAD_ATTR                       20: CP
                        1588    LOAD_ATTR                       22: carFingerprint
                        1608    LOAD_GLOBAL                     24: CAR
                        1618    LOAD_ATTR                       26: CHANGAN_Z6_IDD
                        1638    COMPARE_OP                      40 (==)
                        1642    POP_JUMP_IF_FALSE               108 (to 1860)
                        1644    LOAD_GLOBAL                     57: NULL + int
                        1654    LOAD_FAST                       3: _var_var_1
                        1656    LOAD_ATTR                       12: vl
                        1676    LOAD_CONST                      34: 'GW_338'
                        1678    BINARY_SUBSCR                   
                        1682    LOAD_CONST                      23: 'TCU_GearForDisplay'
                        1684    BINARY_SUBSCR                   
                        1688    CALL                            1
                        1696    STORE_FAST                      8: _var_var_6
                        1698    LOAD_FAST                       3: _var_var_1
                        1700    LOAD_ATTR                       12: vl
                        1720    LOAD_CONST                      35: 'GW_1A6'
                        1722    BINARY_SUBSCR                   
                        1726    LOAD_CONST                      36: 'EMS_BrakePedalStatus'
                        1728    BINARY_SUBSCR                   
                        1732    LOAD_CONST                      18: 0
                        1734    COMPARE_OP                      55 (!=)
                        1738    LOAD_FAST                       5: _var_var_3
                        1740    STORE_ATTR                      29: brakePressed
                        1750    LOAD_FAST                       3: _var_var_1
                        1752    LOAD_ATTR                       12: vl
                        1772    LOAD_CONST                      37: 'GW_1C6'
                        1774    BINARY_SUBSCR                   
                        1778    LOAD_CONST                      33: 'EMS_RealAccPedal'
                        1780    BINARY_SUBSCR                   
                        1784    LOAD_CONST                      18: 0
                        1786    COMPARE_OP                      55 (!=)
                        1790    LOAD_FAST                       5: _var_var_3
                        1792    STORE_ATTR                      30: gasPressed
                        1802    LOAD_CONST                      8: 1
                        1804    LOAD_FAST                       0: self
                        1806    STORE_ATTR                      32: steeringPressedMin
                        1816    LOAD_CONST                      38: 3
                        1818    LOAD_FAST                       0: self
                        1820    STORE_ATTR                      31: steeringPressedMax
                        1830    LOAD_CONST                      9: False
                        1832    LOAD_FAST                       5: _var_var_3
                        1834    STORE_ATTR                      33: leftBlindspot
                        1844    LOAD_CONST                      9: False
                        1846    LOAD_FAST                       5: _var_var_3
                        1848    STORE_ATTR                      34: rightBlindspot
                        1858    JUMP_FORWARD                    107 (to 2074)
                        1860    LOAD_GLOBAL                     57: NULL + int
                        1870    LOAD_FAST                       3: _var_var_1
                        1872    LOAD_ATTR                       12: vl
                        1892    LOAD_CONST                      34: 'GW_338'
                        1894    BINARY_SUBSCR                   
                        1898    LOAD_CONST                      23: 'TCU_GearForDisplay'
                        1900    BINARY_SUBSCR                   
                        1904    CALL                            1
                        1912    STORE_FAST                      8: _var_var_6
                        1914    LOAD_FAST                       3: _var_var_1
                        1916    LOAD_ATTR                       12: vl
                        1936    LOAD_CONST                      39: 'GW_196'
                        1938    BINARY_SUBSCR                   
                        1942    LOAD_CONST                      36: 'EMS_BrakePedalStatus'
                        1944    BINARY_SUBSCR                   
                        1948    LOAD_CONST                      18: 0
                        1950    COMPARE_OP                      55 (!=)
                        1954    LOAD_FAST                       5: _var_var_3
                        1956    STORE_ATTR                      29: brakePressed
                        1966    LOAD_FAST                       3: _var_var_1
                        1968    LOAD_ATTR                       12: vl
                        1988    LOAD_CONST                      39: 'GW_196'
                        1990    BINARY_SUBSCR                   
                        1994    LOAD_CONST                      33: 'EMS_RealAccPedal'
                        1996    BINARY_SUBSCR                   
                        2000    LOAD_CONST                      18: 0
                        2002    COMPARE_OP                      55 (!=)
                        2006    LOAD_FAST                       5: _var_var_3
                        2008    STORE_ATTR                      30: gasPressed
                        2018    LOAD_CONST                      8: 1
                        2020    LOAD_FAST                       0: self
                        2022    STORE_ATTR                      32: steeringPressedMin
                        2032    LOAD_CONST                      40: 6
                        2034    LOAD_FAST                       0: self
                        2036    STORE_ATTR                      31: steeringPressedMax
                        2046    LOAD_CONST                      9: False
                        2048    LOAD_FAST                       5: _var_var_3
                        2050    STORE_ATTR                      33: leftBlindspot
                        2060    LOAD_CONST                      9: False
                        2062    LOAD_FAST                       5: _var_var_3
                        2064    STORE_ATTR                      34: rightBlindspot
                        2074    LOAD_FAST                       0: self
                        2076    LOAD_ATTR                       20: CP
                        2096    LOAD_ATTR                       22: carFingerprint
                        2116    LOAD_GLOBAL                     24: CAR
                        2126    LOAD_ATTR                       28: QIYUAN_A07
                        2146    COMPARE_OP                      40 (==)
                        2150    POP_JUMP_IF_FALSE               42 (to 2236)
                        2152    LOAD_GLOBAL                     6: structs
                        2162    LOAD_ATTR                       8: CarState
                        2182    LOAD_ATTR                       70: GearShifter
                        2202    LOAD_ATTR                       72: drive
                        2222    LOAD_FAST                       5: _var_var_3
                        2224    STORE_ATTR                      37: gearShifter
                        2234    JUMP_FORWARD                    48 (to 2332)
                        2236    LOAD_FAST                       0: self
                        2238    LOAD_ATTR                       77: parse_gear_shifter
                        2258    LOAD_FAST                       0: self
                        2260    LOAD_ATTR                       78: shifter_values
                        2280    LOAD_ATTR                       81: get
                        2300    LOAD_FAST_CHECK                 8: _var_var_6
                        2302    LOAD_CONST                      0: None
                        2304    CALL                            2
                        2312    CALL                            1
                        2320    LOAD_FAST                       5: _var_var_3
                        2322    STORE_ATTR                      37: gearShifter
                        2332    LOAD_FAST                       0: self
                        2334    LOAD_ATTR                       20: CP
                        2354    LOAD_ATTR                       22: carFingerprint
                        2374    LOAD_GLOBAL                     24: CAR
                        2384    LOAD_ATTR                       28: QIYUAN_A07
                        2404    COMPARE_OP                      55 (!=)
                        2408    POP_JUMP_IF_FALSE               70 (to 2550)
                        2410    LOAD_FAST                       0: self
                        2412    LOAD_ATTR                       83: update_blinker_from_stalk
                        2432    LOAD_CONST                      41: 200
                        2434    LOAD_FAST                       3: _var_var_1
                        2436    LOAD_ATTR                       12: vl
                        2456    LOAD_CONST                      4: 'GW_28B'
                        2458    BINARY_SUBSCR                   
                        2462    LOAD_CONST                      42: 'BCM_TurnIndicatorLeft'
                        2464    BINARY_SUBSCR                   
                        2468    LOAD_CONST                      8: 1
                        2470    COMPARE_OP                      40 (==)
                        2474    LOAD_FAST                       3: _var_var_1
                        2476    LOAD_ATTR                       12: vl
                        2496    LOAD_CONST                      4: 'GW_28B'
                        2498    BINARY_SUBSCR                   
                        2502    LOAD_CONST                      43: 'BCM_TurnIndicatorRight'
                        2504    BINARY_SUBSCR                   
                        2508    LOAD_CONST                      8: 1
                        2510    COMPARE_OP                      40 (==)
                        2514    CALL                            3
                        2522    UNPACK_SEQUENCE                 2
                        2526    LOAD_FAST                       5: _var_var_3
                        2528    STORE_ATTR                      42: leftBlinker
                        2538    LOAD_FAST                       5: _var_var_3
                        2540    STORE_ATTR                      43: rightBlinker
                        2550    LOAD_FAST                       3: _var_var_1
                        2552    LOAD_ATTR                       12: vl
                        2572    LOAD_CONST                      44: 'GW_17E'
                        2574    BINARY_SUBSCR                   
                        2578    LOAD_CONST                      45: 'EPS_MeasuredTorsionBarTorque'
                        2580    BINARY_SUBSCR                   
                        2584    LOAD_FAST                       5: _var_var_3
                        2586    STORE_ATTR                      44: steeringTorque
                        2596    LOAD_FAST                       3: _var_var_1
                        2598    LOAD_ATTR                       12: vl
                        2618    LOAD_CONST                      46: 'GW_170'
                        2620    BINARY_SUBSCR                   
                        2624    LOAD_CONST                      47: 'EPS_ActualTorsionBarTorq'
                        2626    BINARY_SUBSCR                   
                        2630    LOAD_FAST                       5: _var_var_3
                        2632    STORE_ATTR                      45: steeringTorqueEps
                        2642    LOAD_FAST                       0: self
                        2644    LOAD_ATTR                       92: steeringPressed
                        2664    POP_JUMP_IF_FALSE               66 (to 2798)
                        2666    LOAD_GLOBAL                     45: NULL + abs
                        2676    LOAD_FAST                       5: _var_var_3
                        2678    LOAD_ATTR                       88: steeringTorque
                        2698    CALL                            1
                        2706    LOAD_FAST                       0: self
                        2708    LOAD_ATTR                       64: steeringPressedMin
                        2728    COMPARE_OP                      2 (<)
                        2732    POP_JUMP_IF_FALSE               73 (to 2880)
                        2734    LOAD_GLOBAL                     45: NULL + abs
                        2744    LOAD_FAST                       5: _var_var_3
                        2746    LOAD_ATTR                       50: steeringAngleDeg
                        2766    CALL                            1
                        2774    LOAD_CONST                      48: 90
                        2776    COMPARE_OP                      2 (<)
                        2780    POP_JUMP_IF_FALSE               49 (to 2880)
                        2782    LOAD_CONST                      9: False
                        2784    LOAD_FAST                       0: self
                        2786    STORE_ATTR                      46: steeringPressed
                        2796    JUMP_FORWARD                    41 (to 2880)
                        2798    LOAD_GLOBAL                     45: NULL + abs
                        2808    LOAD_FAST                       5: _var_var_3
                        2810    LOAD_ATTR                       88: steeringTorque
                        2830    CALL                            1
                        2838    LOAD_FAST                       0: self
                        2840    LOAD_ATTR                       62: steeringPressedMax
                        2860    COMPARE_OP                      68 (>)
                        2864    POP_JUMP_IF_FALSE               7 (to 2880)
                        2866    LOAD_CONST                      49: True
                        2868    LOAD_FAST                       0: self
                        2870    STORE_ATTR                      46: steeringPressed
                        2880    LOAD_FAST                       0: self
                        2882    LOAD_ATTR                       92: steeringPressed
                        2902    LOAD_FAST                       5: _var_var_3
                        2904    STORE_ATTR                      46: steeringPressed
                        2914    LOAD_FAST                       3: _var_var_1
                        2916    LOAD_ATTR                       12: vl
                        2936    LOAD_CONST                      50: 'GW_24F'
                        2938    BINARY_SUBSCR                   
                        2942    LOAD_CONST                      51: 'EPS_EPSFailed'
                        2944    BINARY_SUBSCR                   
                        2948    LOAD_CONST                      18: 0
                        2950    COMPARE_OP                      55 (!=)
                        2954    COPY                            1
                        2956    POP_JUMP_IF_TRUE                21 (to 3000)
                        2958    POP_TOP                         
                        2960    LOAD_FAST                       3: _var_var_1
                        2962    LOAD_ATTR                       12: vl
                        2982    LOAD_CONST                      44: 'GW_17E'
                        2984    BINARY_SUBSCR                   
                        2988    LOAD_CONST                      52: 'EPS_LatCtrlAvailabilityStatus'
                        2990    BINARY_SUBSCR                   
                        2994    LOAD_CONST                      16: 2
                        2996    COMPARE_OP                      40 (==)
                        3000    LOAD_FAST                       5: _var_var_3
                        3002    STORE_ATTR                      47: steerFaultTemporary
                        3012    LOAD_FAST                       0: self
                        3014    LOAD_ATTR                       20: CP
                        3034    LOAD_ATTR                       22: carFingerprint
                        3054    LOAD_GLOBAL                     24: CAR
                        3064    LOAD_ATTR                       54: QIYUAN_A05
                        3084    COMPARE_OP                      40 (==)
                        3088    POP_JUMP_IF_FALSE               69 (to 3228)
                        3090    LOAD_FAST                       3: _var_var_1
                        3092    LOAD_ATTR                       12: vl
                        3112    LOAD_CONST                      53: 'GW_28C'
                        3114    BINARY_SUBSCR                   
                        3118    LOAD_CONST                      54: 'GW_MFS_IACCenable_switch_signal'
                        3120    BINARY_SUBSCR                   
                        3124    LOAD_CONST                      8: 1
                        3126    COMPARE_OP                      40 (==)
                        3130    POP_JUMP_IF_FALSE               7 (to 3146)
                        3132    LOAD_CONST                      49: True
                        3134    LOAD_FAST                       0: self
                        3136    STORE_ATTR                      48: cruiseEnable
                        3146    LOAD_FAST                       3: _var_var_1
                        3148    LOAD_ATTR                       12: vl
                        3168    LOAD_CONST                      53: 'GW_28C'
                        3170    BINARY_SUBSCR                   
                        3174    LOAD_CONST                      55: 'GW_MFS_Cancle_switch_signal'
                        3176    BINARY_SUBSCR                   
                        3180    LOAD_CONST                      8: 1
                        3182    COMPARE_OP                      40 (==)
                        3186    POP_JUMP_IF_TRUE                12 (to 3212)
                        3188    LOAD_FAST                       5: _var_var_3
                        3190    LOAD_ATTR                       58: brakePressed
                        3210    POP_JUMP_IF_FALSE               160 (to 3532)
                        3212    LOAD_CONST                      9: False
                        3214    LOAD_FAST                       0: self
                        3216    STORE_ATTR                      48: cruiseEnable
                        3226    JUMP_FORWARD                    152 (to 3532)
                        3228    LOAD_FAST                       3: _var_var_1
                        3230    LOAD_ATTR                       12: vl
                        3250    LOAD_CONST                      53: 'GW_28C'
                        3252    BINARY_SUBSCR                   
                        3256    LOAD_CONST                      54: 'GW_MFS_IACCenable_switch_signal'
                        3258    BINARY_SUBSCR                   
                        3262    LOAD_FAST                       0: self
                        3264    STORE_ATTR                      49: iacc_enable_switch_button_pressed
                        3274    LOAD_FAST                       0: self
                        3276    LOAD_ATTR                       98: iacc_enable_switch_button_pressed
                        3296    LOAD_CONST                      8: 1
                        3298    COMPARE_OP                      40 (==)
                        3302    COPY                            1
                        3304    POP_JUMP_IF_FALSE               15 (to 3336)
                        3306    POP_TOP                         
                        3308    LOAD_FAST                       0: self
                        3310    LOAD_ATTR                       100: iacc_enable_switch_button_prev
                        3330    LOAD_CONST                      18: 0
                        3332    COMPARE_OP                      40 (==)
                        3336    LOAD_FAST                       0: self
                        3338    STORE_ATTR                      51: iacc_enable_switch_button_rising_edge
                        3348    LOAD_FAST                       0: self
                        3350    LOAD_ATTR                       96: cruiseEnable
                        3370    POP_JUMP_IF_FALSE               32 (to 3436)
                        3372    LOAD_FAST                       0: self
                        3374    LOAD_ATTR                       102: iacc_enable_switch_button_rising_edge
                        3394    POP_JUMP_IF_TRUE                12 (to 3420)
                        3396    LOAD_FAST                       5: _var_var_3
                        3398    LOAD_ATTR                       58: brakePressed
                        3418    POP_JUMP_IF_FALSE               8 (to 3436)
                        3420    LOAD_CONST                      9: False
                        3422    LOAD_FAST                       0: self
                        3424    STORE_ATTR                      48: cruiseEnable
                        3434    JUMP_FORWARD                    31 (to 3498)
                        3436    LOAD_FAST                       0: self
                        3438    LOAD_ATTR                       96: cruiseEnable
                        3458    POP_JUMP_IF_TRUE                19 (to 3498)
                        3460    LOAD_FAST                       0: self
                        3462    LOAD_ATTR                       102: iacc_enable_switch_button_rising_edge
                        3482    POP_JUMP_IF_FALSE               7 (to 3498)
                        3484    LOAD_CONST                      49: True
                        3486    LOAD_FAST                       0: self
                        3488    STORE_ATTR                      48: cruiseEnable
                        3498    LOAD_FAST                       0: self
                        3500    LOAD_ATTR                       98: iacc_enable_switch_button_pressed
                        3520    LOAD_FAST                       0: self
                        3522    STORE_ATTR                      50: iacc_enable_switch_button_prev
                        3532    LOAD_FAST                       0: self
                        3534    LOAD_ATTR                       96: cruiseEnable
                        3554    POP_JUMP_IF_FALSE               19 (to 3594)
                        3556    LOAD_FAST                       0: self
                        3558    LOAD_ATTR                       104: cruiseEnablePrev
                        3578    POP_JUMP_IF_TRUE                7 (to 3594)
                        3580    LOAD_FAST                       7: _var_var_5
                        3582    LOAD_FAST                       0: self
                        3584    STORE_ATTR                      53: cruiseSpeed
                        3594    LOAD_FAST                       3: _var_var_1
                        3596    LOAD_ATTR                       12: vl
                        3616    LOAD_CONST                      53: 'GW_28C'
                        3618    BINARY_SUBSCR                   
                        3622    LOAD_CONST                      56: 'GW_MFS_RESPlus_switch_signal'
                        3624    BINARY_SUBSCR                   
                        3628    LOAD_CONST                      8: 1
                        3630    COMPARE_OP                      40 (==)
                        3634    POP_JUMP_IF_FALSE               53 (to 3742)
                        3636    LOAD_FAST                       0: self
                        3638    LOAD_ATTR                       108: buttonPlus
                        3658    LOAD_CONST                      18: 0
                        3660    COMPARE_OP                      40 (==)
                        3664    POP_JUMP_IF_FALSE               38 (to 3742)
                        3666    LOAD_FAST                       0: self
                        3668    LOAD_ATTR                       96: cruiseEnable
                        3688    POP_JUMP_IF_FALSE               26 (to 3742)
                        3690    LOAD_FAST                       0: self
                        3692    LOAD_ATTR                       106: cruiseSpeed
                        3712    LOAD_CONST                      14: 5
                        3714    BINARY_OP                       2 (//)
                        3718    LOAD_CONST                      8: 1
                        3720    BINARY_OP                       0 (+)
                        3724    LOAD_CONST                      14: 5
                        3726    BINARY_OP                       5 (*)
                        3730    LOAD_FAST                       0: self
                        3732    STORE_ATTR                      53: cruiseSpeed
                        3742    LOAD_FAST                       3: _var_var_1
                        3744    LOAD_ATTR                       12: vl
                        3764    LOAD_CONST                      53: 'GW_28C'
                        3766    BINARY_SUBSCR                   
                        3770    LOAD_CONST                      57: 'GW_MFS_SETReduce_switch_signal'
                        3772    BINARY_SUBSCR                   
                        3776    LOAD_CONST                      8: 1
                        3778    COMPARE_OP                      40 (==)
                        3782    POP_JUMP_IF_FALSE               63 (to 3910)
                        3784    LOAD_FAST                       0: self
                        3786    LOAD_ATTR                       110: buttonReduce
                        3806    LOAD_CONST                      18: 0
                        3808    COMPARE_OP                      40 (==)
                        3812    POP_JUMP_IF_FALSE               48 (to 3910)
                        3814    LOAD_FAST                       0: self
                        3816    LOAD_ATTR                       96: cruiseEnable
                        3836    POP_JUMP_IF_FALSE               36 (to 3910)
                        3838    LOAD_GLOBAL                     113: NULL + max
                        3848    LOAD_FAST                       0: self
                        3850    LOAD_ATTR                       106: cruiseSpeed
                        3870    LOAD_CONST                      14: 5
                        3872    BINARY_OP                       2 (//)
                        3876    LOAD_CONST                      8: 1
                        3878    BINARY_OP                       10 (-)
                        3882    LOAD_CONST                      14: 5
                        3884    BINARY_OP                       5 (*)
                        3888    LOAD_CONST                      18: 0
                        3890    CALL                            2
                        3898    LOAD_FAST                       0: self
                        3900    STORE_ATTR                      53: cruiseSpeed
                        3910    LOAD_FAST                       0: self
                        3912    LOAD_ATTR                       96: cruiseEnable
                        3932    LOAD_FAST                       0: self
                        3934    STORE_ATTR                      52: cruiseEnablePrev
                        3944    LOAD_FAST                       3: _var_var_1
                        3946    LOAD_ATTR                       12: vl
                        3966    LOAD_CONST                      53: 'GW_28C'
                        3968    BINARY_SUBSCR                   
                        3972    LOAD_CONST                      56: 'GW_MFS_RESPlus_switch_signal'
                        3974    BINARY_SUBSCR                   
                        3978    LOAD_FAST                       0: self
                        3980    STORE_ATTR                      54: buttonPlus
                        3990    LOAD_FAST                       3: _var_var_1
                        3992    LOAD_ATTR                       12: vl
                        4012    LOAD_CONST                      53: 'GW_28C'
                        4014    BINARY_SUBSCR                   
                        4018    LOAD_CONST                      57: 'GW_MFS_SETReduce_switch_signal'
                        4020    BINARY_SUBSCR                   
                        4024    LOAD_FAST                       0: self
                        4026    STORE_ATTR                      55: buttonReduce
                        4036    LOAD_FAST                       4: _var_var_2
                        4038    LOAD_ATTR                       12: vl
                        4058    LOAD_CONST                      58: 'GW_244'
                        4060    BINARY_SUBSCR                   
                        4064    LOAD_CONST                      59: 'ACC_ACCMode'
                        4066    BINARY_SUBSCR                   
                        4070    LOAD_CONST                      60: 7
                        4072    COMPARE_OP                      40 (==)
                        4076    COPY                            1
                        4078    POP_JUMP_IF_TRUE                21 (to 4122)
                        4080    POP_TOP                         
                        4082    LOAD_FAST                       4: _var_var_2
                        4084    LOAD_ATTR                       12: vl
                        4104    LOAD_CONST                      61: 'GW_31A'
                        4106    BINARY_SUBSCR                   
                        4110    LOAD_CONST                      62: 'ACC_IACCHWAMode'
                        4112    BINARY_SUBSCR                   
                        4116    LOAD_CONST                      60: 7
                        4118    COMPARE_OP                      40 (==)
                        4122    LOAD_FAST                       5: _var_var_3
                        4124    STORE_ATTR                      57: accFaulted
                        4134    LOAD_FAST                       4: _var_var_2
                        4136    LOAD_ATTR                       12: vl
                        4156    LOAD_CONST                      61: 'GW_31A'
                        4158    BINARY_SUBSCR                   
                        4162    LOAD_CONST                      63: 'ACC_IACCHWAEnable'
                        4164    BINARY_SUBSCR                   
                        4168    LOAD_CONST                      8: 1
                        4170    COMPARE_OP                      40 (==)
                        4174    LOAD_FAST                       5: _var_var_3
                        4176    LOAD_ATTR                       116: cruiseState
                        4196    STORE_ATTR                      59: available
                        4206    LOAD_FAST                       0: self
                        4208    LOAD_ATTR                       106: cruiseSpeed
                        4228    LOAD_GLOBAL                     30: CV
                        4238    LOAD_ATTR                       32: KPH_TO_MS
                        4258    BINARY_OP                       5 (*)
                        4262    LOAD_FAST                       5: _var_var_3
                        4264    LOAD_ATTR                       116: cruiseState
                        4284    STORE_ATTR                      60: speed
                        4294    LOAD_FAST                       0: self
                        4296    LOAD_ATTR                       106: cruiseSpeed
                        4316    STORE_FAST                      9: _var_var_7
                        4318    LOAD_FAST                       5: _var_var_3
                        4320    LOAD_ATTR                       116: cruiseState
                        4340    LOAD_ATTR                       120: speed
                        4360    LOAD_CONST                      18: 0
                        4362    COMPARE_OP                      55 (!=)
                        4366    POP_JUMP_IF_FALSE               34 (to 4436)
                        4368    LOAD_FAST                       9: _var_var_7
                        4370    LOAD_GLOBAL                     30: CV
                        4380    LOAD_ATTR                       32: KPH_TO_MS
                        4400    BINARY_OP                       5 (*)
                        4404    LOAD_FAST                       5: _var_var_3
                        4406    LOAD_ATTR                       116: cruiseState
                        4426    STORE_ATTR                      61: speedCluster
                        4436    LOAD_FAST                       4: _var_var_2
                        4438    LOAD_ATTR                       12: vl
                        4458    LOAD_CONST                      58: 'GW_244'
                        4460    BINARY_SUBSCR                   
                        4464    LOAD_CONST                      64: 'ACC_FCWPreWarning'
                        4466    BINARY_SUBSCR                   
                        4470    LOAD_CONST                      8: 1
                        4472    COMPARE_OP                      40 (==)
                        4476    LOAD_FAST                       5: _var_var_3
                        4478    STORE_ATTR                      62: stockFcw
                        4488    LOAD_FAST                       5: _var_var_3
                        4490    LOAD_ATTR                       46: standstill
                        4510    LOAD_FAST                       5: _var_var_3
                        4512    LOAD_ATTR                       116: cruiseState
                        4532    STORE_ATTR                      23: standstill
                        4542    LOAD_FAST                       0: self
                        4544    LOAD_ATTR                       96: cruiseEnable
                        4564    LOAD_FAST                       5: _var_var_3
                        4566    LOAD_ATTR                       116: cruiseState
                        4586    STORE_ATTR                      63: enabled
                        4596    LOAD_CONST                      9: False
                        4598    LOAD_FAST                       5: _var_var_3
                        4600    STORE_ATTR                      64: genericToggle
                        4610    LOAD_FAST                       4: _var_var_2
                        4612    LOAD_ATTR                       12: vl
                        4632    LOAD_CONST                      58: 'GW_244'
                        4634    BINARY_SUBSCR                   
                        4638    LOAD_CONST                      65: 'ACC_AEBCtrlType'
                        4640    BINARY_SUBSCR                   
                        4644    LOAD_CONST                      18: 0
                        4646    COMPARE_OP                      68 (>)
                        4650    LOAD_FAST                       5: _var_var_3
                        4652    STORE_ATTR                      65: stockAeb
                        4662    LOAD_GLOBAL                     133: NULL + copy
                        4672    LOAD_ATTR                       132: copy
                        4692    LOAD_FAST                       4: _var_var_2
                        4694    LOAD_ATTR                       12: vl
                        4714    LOAD_CONST                      58: 'GW_244'
                        4716    BINARY_SUBSCR                   
                        4720    CALL                            1
                        4728    LOAD_FAST                       0: self
                        4730    STORE_ATTR                      67: sigs244
                        4740    LOAD_GLOBAL                     133: NULL + copy
                        4750    LOAD_ATTR                       132: copy
                        4770    LOAD_FAST                       4: _var_var_2
                        4772    LOAD_ATTR                       12: vl
                        4792    LOAD_CONST                      66: 'GW_1BA'
                        4794    BINARY_SUBSCR                   
                        4798    CALL                            1
                        4806    LOAD_FAST                       0: self
                        4808    STORE_ATTR                      68: sigs1ba
                        4818    LOAD_GLOBAL                     133: NULL + copy
                        4828    LOAD_ATTR                       132: copy
                        4848    LOAD_FAST                       3: _var_var_1
                        4850    LOAD_ATTR                       12: vl
                        4870    LOAD_CONST                      44: 'GW_17E'
                        4872    BINARY_SUBSCR                   
                        4876    CALL                            1
                        4884    LOAD_FAST                       0: self
                        4886    STORE_ATTR                      69: sigs17e
                        4896    LOAD_GLOBAL                     133: NULL + copy
                        4906    LOAD_ATTR                       132: copy
                        4926    LOAD_FAST                       4: _var_var_2
                        4928    LOAD_ATTR                       12: vl
                        4948    LOAD_CONST                      67: 'GW_307'
                        4950    BINARY_SUBSCR                   
                        4954    CALL                            1
                        4962    LOAD_FAST                       0: self
                        4964    STORE_ATTR                      70: sigs307
                        4974    LOAD_GLOBAL                     133: NULL + copy
                        4984    LOAD_ATTR                       132: copy
                        5004    LOAD_FAST                       4: _var_var_2
                        5006    LOAD_ATTR                       12: vl
                        5026    LOAD_CONST                      61: 'GW_31A'
                        5028    BINARY_SUBSCR                   
                        5032    CALL                            1
                        5040    LOAD_FAST                       0: self
                        5042    STORE_ATTR                      71: sigs31a
                        5052    LOAD_FAST                       4: _var_var_2
                        5054    LOAD_ATTR                       12: vl
                        5074    LOAD_CONST                      58: 'GW_244'
                        5076    BINARY_SUBSCR                   
                        5080    LOAD_CONST                      68: 'ACC_RollingCounter_24E'
                        5082    BINARY_SUBSCR                   
                        5086    LOAD_FAST                       0: self
                        5088    STORE_ATTR                      72: counter_244
                        5098    LOAD_FAST                       4: _var_var_2
                        5100    LOAD_ATTR                       12: vl
                        5120    LOAD_CONST                      66: 'GW_1BA'
                        5122    BINARY_SUBSCR                   
                        5126    LOAD_CONST                      69: 'ACC_RollingCounter_1BA'
                        5128    BINARY_SUBSCR                   
                        5132    LOAD_FAST                       0: self
                        5134    STORE_ATTR                      73: counter_1ba
                        5144    LOAD_FAST                       3: _var_var_1
                        5146    LOAD_ATTR                       12: vl
                        5166    LOAD_CONST                      44: 'GW_17E'
                        5168    BINARY_SUBSCR                   
                        5172    LOAD_CONST                      70: 'EPS_RollingCounter_17E'
                        5174    BINARY_SUBSCR                   
                        5178    LOAD_FAST                       0: self
                        5180    STORE_ATTR                      74: counter_17e
                        5190    LOAD_FAST                       4: _var_var_2
                        5192    LOAD_ATTR                       12: vl
                        5212    LOAD_CONST                      67: 'GW_307'
                        5214    BINARY_SUBSCR                   
                        5218    LOAD_CONST                      71: 'ACC_RollingCounter_35E'
                        5220    BINARY_SUBSCR                   
                        5224    LOAD_FAST                       0: self
                        5226    STORE_ATTR                      75: counter_307
                        5236    LOAD_FAST                       4: _var_var_2
                        5238    LOAD_ATTR                       12: vl
                        5258    LOAD_CONST                      61: 'GW_31A'
                        5260    BINARY_SUBSCR                   
                        5264    LOAD_CONST                      72: 'ACC_RollingCounter_36D'
                        5266    BINARY_SUBSCR                   
                        5270    LOAD_FAST                       0: self
                        5272    STORE_ATTR                      76: counter_31a
                        5282    LOAD_FAST                       0: self
                        5284    LOAD_ATTR                       154: distance_button
                        5304    LOAD_FAST                       0: self
                        5306    STORE_ATTR                      78: prev_distance_button
                        5316    LOAD_FAST                       4: _var_var_2
                        5318    LOAD_ATTR                       12: vl
                        5338    LOAD_CONST                      67: 'GW_307'
                        5340    BINARY_SUBSCR                   
                        5344    LOAD_CONST                      73: 'ACC_DistanceLevel'
                        5346    BINARY_SUBSCR                   
                        5350    LOAD_FAST                       0: self
                        5352    STORE_ATTR                      77: distance_button
                        5362    LOAD_FAST                       5: _var_var_3
                        5364    NOP                             
                        5366    NOP                             
                        5368    NOP                             
                        5370    JUMP_FORWARD                    20 (to 5412)
                        5372    CALL                            1
                        5380    POP_TOP                         
                        5382    RETURN_VALUE                    
                        5384    PUSH_EXC_INFO                   
                        5386    PUSH_NULL                       
                        5388    LOAD_CONST                      74: '__pyarmor_exit_41375__'
                        5390    NOP                             
                        5392    LOAD_CONST                      3: b'<COAddr>\x01\x00\x00\x1a\xee\x14\x00\x00\x00\x00\x00\x00'
                        5394    CALL                            1
                        5402    POP_TOP                         
                        5404    RERAISE                         0
                        5406    COPY                            3
                        5408    POP_EXCEPT                      
                        5410    RERAISE                         1
                        5412    PUSH_NULL                       
                        5414    LOAD_CONST                      74: '__pyarmor_exit_41375__'
                        5416    LOAD_CONST                      3: b'<COAddr>\x01\x00\x00\x1a\xee\x14\x00\x00\x00\x00\x00\x00'
                        5418    BUILD_TUPLE                     1
                        5420    CALL_FUNCTION_EX                0
                        5422    POP_TOP                         
                        5424    RETURN_VALUE                    
                    [Exception Table]
                        28 to 5364 -> 5384 [0] 
                        5384 to 5406 -> 5406 [1] lasti
                [Code]
                    File Name: <frozen changan.carstate>
                    Object Name: get_can_parsers
                    Qualified Name: CarState.get_can_parsers
                    Arg Count: 1
                    Pos Only Arg Count: 0
                    KW Only Arg Count: 0
                    Stack Size: 8
                    Flags: 0x20000003 (CO_OPTIMIZED | CO_NEWLOCALS | CO_PYARMOR_OBFUSCATED)
                    [Names]
                        'Bus'
                        'pt'
                        'CANParser'
                        'DBC'
                        'carFingerprint'
                        'cam'
                    [Locals+Names]
                        'CP'
                        '__assert_armored__'
                    [Constants]
                        None
                        '__pyarmor_assert_41376__'
                        '__pyarmor_enter_41377__'
                        b'<COAddr>\x01\x00\x00\x1a\x0c\x01\x00\x00\x00\x00\x00\x00'
                        0
                        2
                        '__pyarmor_exit_41378__'
                    [Disassembly]
                        0       NOP                             
                        2       NOP                             
                        4       PUSH_NULL                       
                        6       LOAD_CONST                      2: '__pyarmor_enter_41377__'
                        8       LOAD_CONST                      3: b'<COAddr>\x01\x00\x00\x1a\x0c\x01\x00\x00\x00\x00\x00\x00'
                        10      BUILD_TUPLE                     1
                        12      CALL_FUNCTION_EX                0
                        14      POP_TOP                         
                        16      RESUME                          0
                        18      NOP                             
                        20      NOP                             
                        22      NOP                             
                        24      NOP                             
                        26      NOP                             
                        28      LOAD_GLOBAL                     0: Bus
                        38      LOAD_ATTR                       2: pt
                        58      LOAD_GLOBAL                     5: NULL + CANParser
                        68      LOAD_GLOBAL                     6: DBC
                        78      LOAD_FAST                       0: CP
                        80      LOAD_ATTR                       8: carFingerprint
                        100     BINARY_SUBSCR                   
                        104     LOAD_GLOBAL                     0: Bus
                        114     LOAD_ATTR                       2: pt
                        134     BINARY_SUBSCR                   
                        138     BUILD_LIST                      0
                        140     LOAD_CONST                      4: 0
                        142     CALL                            3
                        150     LOAD_GLOBAL                     0: Bus
                        160     LOAD_ATTR                       10: cam
                        180     LOAD_GLOBAL                     5: NULL + CANParser
                        190     LOAD_GLOBAL                     6: DBC
                        200     LOAD_FAST                       0: CP
                        202     LOAD_ATTR                       8: carFingerprint
                        222     BINARY_SUBSCR                   
                        226     LOAD_GLOBAL                     0: Bus
                        236     LOAD_ATTR                       2: pt
                        256     BINARY_SUBSCR                   
                        260     BUILD_LIST                      0
                        262     LOAD_CONST                      5: 2
                        264     CALL                            3
                        272     BUILD_MAP                       2
                        274     NOP                             
                        276     NOP                             
                        278     NOP                             
                        280     JUMP_FORWARD                    20 (to 322)
                        282     CALL                            1
                        290     POP_TOP                         
                        292     RETURN_VALUE                    
                        294     PUSH_EXC_INFO                   
                        296     PUSH_NULL                       
                        298     LOAD_CONST                      6: '__pyarmor_exit_41378__'
                        300     NOP                             
                        302     LOAD_CONST                      3: b'<COAddr>\x01\x00\x00\x1a\x0c\x01\x00\x00\x00\x00\x00\x00'
                        304     CALL                            1
                        312     POP_TOP                         
                        314     RERAISE                         0
                        316     COPY                            3
                        318     POP_EXCEPT                      
                        320     RERAISE                         1
                        322     PUSH_NULL                       
                        324     LOAD_CONST                      6: '__pyarmor_exit_41378__'
                        326     LOAD_CONST                      3: b'<COAddr>\x01\x00\x00\x1a\x0c\x01\x00\x00\x00\x00\x00\x00'
                        328     BUILD_TUPLE                     1
                        330     CALL_FUNCTION_EX                0
                        332     POP_TOP                         
                        334     RETURN_VALUE                    
                    [Exception Table]
                        28 to 274 -> 294 [0] 
                        294 to 316 -> 316 [1] lasti
                '__pyarmor_exit_41369__'
            [Disassembly]
                0       MAKE_CELL                       0: __class__
                2       NOP                             
                4       LOAD_NAME                       0: __name__
                6       STORE_NAME                      1: __module__
                8       LOAD_CONST                      0: 'CarState'
                10      STORE_NAME                      2: __qualname__
                12      NOP                             
                14      PUSH_NULL                       
                16      LOAD_CONST                      2: '__pyarmor_enter_41368__'
                18      LOAD_CONST                      3: b'<COAddr>\x03\x00\x00$V\x00\x00\x00\x00\x00\x00\x00'
                20      BUILD_TUPLE                     1
                22      CALL_FUNCTION_EX                0
                24      POP_TOP                         
                26      RESUME                          0
                28      NOP                             
                30      NOP                             
                32      NOP                             
                34      NOP                             
                36      NOP                             
                38      LOAD_CLOSURE                    0: __class__
                40      BUILD_TUPLE                     1
                42      LOAD_CONST                      4: <CODE> __init__
                44      MAKE_FUNCTION                   8
                46      STORE_NAME                      4: __init__
                48      LOAD_CONST                      5: 'return'
                50      LOAD_NAME                       5: structs
                52      LOAD_ATTR                       12: CarState
                72      BUILD_TUPLE                     2
                74      LOAD_CONST                      6: <CODE> update
                76      MAKE_FUNCTION                   4
                78      STORE_NAME                      7: update
                80      LOAD_NAME                       8: staticmethod
                82      LOAD_CONST                      7: <CODE> get_can_parsers
                84      MAKE_FUNCTION                   0
                86      CALL                            0
                94      STORE_NAME                      9: get_can_parsers
                96      LOAD_CLOSURE                    0: __class__
                98      COPY                            1
                100     STORE_NAME                      10: __classcell__
                102     NOP                             
                104     NOP                             
                106     NOP                             
                108     JUMP_FORWARD                    20 (to 150)
                112     POP_TOP                         
                114     LOAD_CLOSURE                    0: __class__
                116     COPY                            1
                118     STORE_NAME                      10: __classcell__
                120     RETURN_VALUE                    
                122     PUSH_EXC_INFO                   
                124     PUSH_NULL                       
                126     LOAD_CONST                      8: '__pyarmor_exit_41369__'
                128     NOP                             
                130     LOAD_CONST                      3: b'<COAddr>\x03\x00\x00$V\x00\x00\x00\x00\x00\x00\x00'
                132     CALL                            1
                140     POP_TOP                         
                142     RERAISE                         0
                144     COPY                            3
                146     POP_EXCEPT                      
                148     RERAISE                         1
                150     PUSH_NULL                       
                152     LOAD_CONST                      8: '__pyarmor_exit_41369__'
                154     LOAD_CONST                      3: b'<COAddr>\x03\x00\x00$V\x00\x00\x00\x00\x00\x00\x00'
                156     BUILD_TUPLE                     1
                158     CALL_FUNCTION_EX                0
                160     POP_TOP                         
                162     RETURN_VALUE                    
            [Exception Table]
                38 to 96 -> 122 [0] 
                122 to 144 -> 144 [1] lasti
        'CarState'
        '__pyarmor_exit_41366__'
    [Disassembly]
        0       NOP                             
        2       NOP                             
        4       PUSH_NULL                       
        6       LOAD_CONST                      1: '__pyarmor_enter_41365__'
        8       LOAD_CONST                      2: b'<COAddr>\x03\x00\x00\x1a\xd6\x00\x00\x00\x00\x00\x00\x00'
        10      BUILD_TUPLE                     1
        12      CALL_FUNCTION_EX                0
        14      POP_TOP                         
        16      RESUME                          0
        18      NOP                             
        20      NOP                             
        22      NOP                             
        24      NOP                             
        26      LOAD_CONST                      3: 0
        28      LOAD_CONST                      4: None
        30      IMPORT_NAME                     1: copy
        32      STORE_NAME                      1: copy
        34      LOAD_CONST                      3: 0
        36      LOAD_CONST                      4: None
        38      IMPORT_NAME                     2: time
        40      STORE_NAME                      2: time
        42      LOAD_CONST                      3: 0
        44      LOAD_CONST                      5: ('Conversions',)
        46      IMPORT_NAME                     3: opendbc.car.common.conversions
        48      IMPORT_FROM                     4: Conversions
        50      STORE_NAME                      5: CV
        52      POP_TOP                         
        54      LOAD_CONST                      3: 0
        56      LOAD_CONST                      6: ('FirstOrderFilter',)
        58      IMPORT_NAME                     6: openpilot.common.filter_simple
        60      IMPORT_FROM                     7: FirstOrderFilter
        62      STORE_NAME                      7: FirstOrderFilter
        64      POP_TOP                         
        66      LOAD_CONST                      3: 0
        68      LOAD_CONST                      7: ('DT_CTRL',)
        70      IMPORT_NAME                     8: openpilot.common.realtime
        72      IMPORT_FROM                     9: DT_CTRL
        74      STORE_NAME                      9: DT_CTRL
        76      POP_TOP                         
        78      LOAD_CONST                      3: 0
        80      LOAD_CONST                      8: ('CANDefine', 'CANParser')
        82      IMPORT_NAME                     10: opendbc.can
        84      IMPORT_FROM                     11: CANDefine
        86      STORE_NAME                      11: CANDefine
        88      IMPORT_FROM                     12: CANParser
        90      STORE_NAME                      12: CANParser
        92      POP_TOP                         
        94      LOAD_CONST                      3: 0
        96      LOAD_CONST                      9: ('CarStateBase',)
        98      IMPORT_NAME                     13: opendbc.car.interfaces
        100     IMPORT_FROM                     14: CarStateBase
        102     STORE_NAME                      14: CarStateBase
        104     POP_TOP                         
        106     LOAD_CONST                      3: 0
        108     LOAD_CONST                      10: ('CAR', 'DBC', 'STEER_THRESHOLD', 'EPS_SCALE')
        110     IMPORT_NAME                     15: opendbc.car.changan.values
        112     IMPORT_FROM                     16: CAR
        114     STORE_NAME                      16: CAR
        116     IMPORT_FROM                     17: DBC
        118     STORE_NAME                      17: DBC
        120     IMPORT_FROM                     18: STEER_THRESHOLD
        122     STORE_NAME                      18: STEER_THRESHOLD
        124     IMPORT_FROM                     19: EPS_SCALE
        126     STORE_NAME                      19: EPS_SCALE
        128     POP_TOP                         
        130     LOAD_CONST                      3: 0
        132     LOAD_CONST                      11: ('Bus', 'structs')
        134     IMPORT_NAME                     20: opendbc.car
        136     IMPORT_FROM                     21: Bus
        138     STORE_NAME                      21: Bus
        140     IMPORT_FROM                     22: structs
        142     STORE_NAME                      22: structs
        144     POP_TOP                         
        146     LOAD_NAME                       22: structs
        148     LOAD_ATTR                       46: CarParams
        168     LOAD_ATTR                       48: SteerControlType
        188     STORE_NAME                      24: SteerControlType
        190     LOAD_CONST                      12: (0, 9, 11, 21, 25)
        192     STORE_NAME                      25: TEMP_STEER_FAULTS
        194     LOAD_CONST                      13: (3, 17)
        196     STORE_NAME                      26: PERM_STEER_FAULTS
        198     PUSH_NULL                       
        200     LOAD_BUILD_CLASS                
        202     LOAD_CONST                      14: <CODE> CarState
        204     MAKE_FUNCTION                   0
        206     LOAD_CONST                      15: 'CarState'
        208     LOAD_NAME                       14: CarStateBase
        210     CALL                            3
        218     STORE_NAME                      27: CarState
        220     LOAD_CONST                      4: None
        222     NOP                             
        224     NOP                             
        226     NOP                             
        228     JUMP_FORWARD                    19 (to 268)
        236     POP_TOP                         
        238     RETURN_CONST                    4: None
        240     PUSH_EXC_INFO                   
        242     PUSH_NULL                       
        244     LOAD_CONST                      16: '__pyarmor_exit_41366__'
        246     NOP                             
        248     LOAD_CONST                      2: b'<COAddr>\x03\x00\x00\x1a\xd6\x00\x00\x00\x00\x00\x00\x00'
        250     CALL                            1
        258     POP_TOP                         
        260     RERAISE                         0
        262     COPY                            3
        264     POP_EXCEPT                      
        266     RERAISE                         1
        268     PUSH_NULL                       
        270     LOAD_CONST                      16: '__pyarmor_exit_41366__'
        272     LOAD_CONST                      2: b'<COAddr>\x03\x00\x00\x1a\xd6\x00\x00\x00\x00\x00\x00\x00'
        274     BUILD_TUPLE                     1
        276     CALL_FUNCTION_EX                0
        278     POP_TOP                         
        280     RETURN_VALUE                    
    [Exception Table]
        26 to 220 -> 240 [0] 
        240 to 262 -> 262 [1] lasti
