# File: changancan.py.1shot.seq (Python 3.12)
# Disassembly generated by Pyarmor-Static-Unpack-1shot (v0.3.0), powered by pycdas

# ================================
# Pyarmor notes:
# - Pyarmor bytecode and code objects match standard Python, but special calls to Pyarmor runtime functions exist.
# - Calls on strings are not mistakes but markers, which are processed by Pyarmor at runtime.
#
# Decompilation guidance (without runtime):
# 1. Ignore encrypted bytes after `#`; use only the string before `#`.
# 2. Remove `"__pyarmor_enter_xxx__"(b"<COAddr>...")` and `"__pyarmor_leave_xxx__"(b"<COAddr>...")` (prologue/epilogue).
# 3. `"__pyarmor_assert_xxx__"(A)` is not a real assert statement.
#    - If `A` is a name or readable string: replace with `A`.
#    - If `A` is `(X, "Y")`: replace with `X.Y`.
#    - If `A` is `(X, "Y", Z)`: replace with `X.Y = Z`.
#    - Otherwise: choose the most reasonable replacement.
# 4. `"__pyarmor_bcc_xxx__"(...)` indicates native code; function body is not available. Add a comment.
# ================================

[Code]
    File Name: <frozen changan.changancan>
    Object Name: <module>
    Qualified Name: <module>
    Arg Count: 0
    Pos Only Arg Count: 0
    KW Only Arg Count: 0
    Stack Size: 5
    Flags: 0x20000000 (CO_PYARMOR_OBFUSCATED)
    [Names]
        '__assert_armored__'
        'crc8_tab'
        'crc_calculate_crc8'
        'bytes'
        'int'
        'crc16_ccitt_false'
        'create_244_command_a05'
        'dict'
        'create_244_command'
        'create_244_command_idd'
        'create_1BA_command'
        'create_17E_command'
        'create_307_command'
        'create_31A_command'
    [Locals+Names]
    [Constants]
        '__pyarmor_assert_41391__'
        '__pyarmor_enter_41392__'
        b'<COAddr>\x01\x00\x00\x1a\x82\x00\x00\x00\x00\x00\x00\x00'
        (
            0
            29
            58
            39
            116
            105
            78
            83
            232
            245
            210
            207
            156
            129
            166
            187
            205
            208
            247
            234
            185
            164
            131
            158
            37
            56
            31
            2
            81
            76
            107
            118
            135
            154
            189
            160
            243
            238
            201
            212
            111
            114
            85
            72
            27
            6
            33
            60
            74
            87
            112
            109
            62
            35
            4
            25
            162
            191
            152
            133
            214
            203
            236
            241
            19
            14
            41
            52
            103
            122
            93
            64
            251
            230
            193
            220
            143
            146
            181
            168
            222
            195
            228
            249
            170
            183
            144
            141
            54
            43
            12
            17
            66
            95
            120
            101
            148
            137
            174
            179
            224
            253
            218
            199
            124
            97
            70
            91
            8
            21
            50
            47
            89
            68
            99
            126
            45
            48
            23
            10
            177
            172
            139
            150
            197
            216
            255
            226
            38
            59
            28
            1
            82
            79
            104
            117
            206
            211
            244
            233
            186
            167
            128
            157
            235
            246
            209
            204
            159
            130
            165
            184
            3
            30
            57
            36
            119
            106
            77
            80
            161
            188
            155
            134
            213
            200
            239
            242
            73
            84
            115
            110
            61
            32
            7
            26
            108
            113
            86
            75
            24
            5
            34
            63
            132
            153
            190
            163
            240
            237
            202
            215
            53
            40
            15
            18
            65
            92
            123
            102
            221
            192
            231
            250
            169
            180
            147
            142
            248
            229
            194
            223
            140
            145
            182
            171
            16
            13
            42
            55
            100
            121
            94
            67
            178
            175
            136
            149
            198
            219
            252
            225
            90
            71
            96
            125
            46
            51
            20
            9
            127
            98
            69
            88
            11
            22
            49
            44
            151
            138
            173
            176
            227
            254
            217
            196
        )
        [Code]
            File Name: <frozen changan.changancan>
            Object Name: crc_calculate_crc8
            Qualified Name: crc_calculate_crc8
            Arg Count: 1
            Pos Only Arg Count: 0
            KW Only Arg Count: 0
            Stack Size: 5
            Flags: 0x20000003 (CO_OPTIMIZED | CO_NEWLOCALS | CO_PYARMOR_OBFUSCATED)
            [Names]
                'crc8_tab'
            [Locals+Names]
                'data'
                '__assert_armored__'
                '_var_var_0'
                '_var_var_1'
            [Constants]
                None
                '__pyarmor_assert_41394__'
                '__pyarmor_enter_41395__'
                b'<COAddr>\x01\x00\x00\x1aH\x00\x00\x00\x00\x00\x00\x00'
                255
                '__pyarmor_exit_41396__'
            [Disassembly]
                0       NOP                             
                2       NOP                             
                4       PUSH_NULL                       
                6       LOAD_CONST                      2: '__pyarmor_enter_41395__'
                8       LOAD_CONST                      3: b'<COAddr>\x01\x00\x00\x1aH\x00\x00\x00\x00\x00\x00\x00'
                10      BUILD_TUPLE                     1
                12      CALL_FUNCTION_EX                0
                14      POP_TOP                         
                16      RESUME                          0
                18      NOP                             
                20      NOP                             
                22      NOP                             
                24      NOP                             
                26      NOP                             
                28      LOAD_CONST                      4: 255
                30      STORE_FAST                      2: _var_var_0
                32      LOAD_FAST                       0: data
                34      GET_ITER                        
                36      FOR_ITER                        14 (to 66)
                40      STORE_FAST                      3: _var_var_1
                42      LOAD_GLOBAL                     0: crc8_tab
                52      LOAD_FAST                       2: _var_var_0
                54      LOAD_FAST                       3: _var_var_1
                56      BINARY_OP                       12 (^)
                60      BINARY_SUBSCR                   
                64      STORE_FAST                      2: _var_var_0
                66      JUMP_BACKWARD                   16 (to 36)
                68      END_FOR                         
                70      LOAD_FAST                       2: _var_var_0
                72      LOAD_CONST                      4: 255
                74      BINARY_OP                       12 (^)
                78      NOP                             
                80      NOP                             
                82      NOP                             
                84      JUMP_FORWARD                    20 (to 126)
                86      CALL                            1
                94      POP_TOP                         
                96      RETURN_VALUE                    
                98      PUSH_EXC_INFO                   
                100     PUSH_NULL                       
                102     LOAD_CONST                      5: '__pyarmor_exit_41396__'
                104     NOP                             
                106     LOAD_CONST                      3: b'<COAddr>\x01\x00\x00\x1aH\x00\x00\x00\x00\x00\x00\x00'
                108     CALL                            1
                116     POP_TOP                         
                118     RERAISE                         0
                120     COPY                            3
                122     POP_EXCEPT                      
                124     RERAISE                         1
                126     PUSH_NULL                       
                128     LOAD_CONST                      5: '__pyarmor_exit_41396__'
                130     LOAD_CONST                      3: b'<COAddr>\x01\x00\x00\x1aH\x00\x00\x00\x00\x00\x00\x00'
                132     BUILD_TUPLE                     1
                134     CALL_FUNCTION_EX                0
                136     POP_TOP                         
                138     RETURN_VALUE                    
            [Exception Table]
                28 to 78 -> 98 [0] 
                98 to 120 -> 120 [1] lasti
        'data'
        'return'
        [Code]
            File Name: <frozen changan.changancan>
            Object Name: crc16_ccitt_false
            Qualified Name: crc16_ccitt_false
            Arg Count: 3
            Pos Only Arg Count: 0
            KW Only Arg Count: 0
            Stack Size: 5
            Flags: 0x20000003 (CO_OPTIMIZED | CO_NEWLOCALS | CO_PYARMOR_OBFUSCATED)
            [Names]
                'range'
            [Locals+Names]
                'data'
                'poly'
                'init_val'
                '__assert_armored__'
                '_var_var_0'
                '_var_var_1'
                '_var_var_2'
            [Constants]
                None
                '__pyarmor_assert_41397__'
                '__pyarmor_enter_41398__'
                b'<COAddr>\x03\x00\x00\x1a\x8a\x00\x00\x00\x00\x00\x00\x00'
                8
                32768
                1
                65535
                '__pyarmor_exit_41399__'
            [Disassembly]
                0       NOP                             
                2       NOP                             
                4       PUSH_NULL                       
                6       LOAD_CONST                      2: '__pyarmor_enter_41398__'
                8       LOAD_CONST                      3: b'<COAddr>\x03\x00\x00\x1a\x8a\x00\x00\x00\x00\x00\x00\x00'
                10      BUILD_TUPLE                     1
                12      CALL_FUNCTION_EX                0
                14      POP_TOP                         
                16      RESUME                          0
                18      NOP                             
                20      NOP                             
                22      NOP                             
                24      NOP                             
                26      NOP                             
                28      LOAD_FAST                       2: init_val
                30      STORE_FAST                      4: _var_var_0
                32      LOAD_FAST                       0: data
                34      GET_ITER                        
                36      FOR_ITER                        50 (to 138)
                40      STORE_FAST                      5: _var_var_1
                42      LOAD_FAST                       4: _var_var_0
                44      LOAD_FAST                       5: _var_var_1
                46      LOAD_CONST                      4: 8
                48      BINARY_OP                       3 (<<)
                52      BINARY_OP                       25 (^=)
                56      STORE_FAST                      4: _var_var_0
                58      LOAD_GLOBAL                     1: NULL + range
                68      LOAD_CONST                      4: 8
                70      CALL                            1
                78      GET_ITER                        
                80      FOR_ITER                        26 (to 134)
                84      STORE_FAST                      6: _var_var_2
                86      LOAD_FAST                       4: _var_var_0
                88      LOAD_CONST                      5: 32768
                90      BINARY_OP                       1 (&)
                94      POP_JUMP_IF_FALSE               9 (to 114)
                96      LOAD_FAST                       4: _var_var_0
                98      LOAD_CONST                      6: 1
                100     BINARY_OP                       3 (<<)
                104     LOAD_FAST                       1: poly
                106     BINARY_OP                       12 (^)
                110     STORE_FAST                      4: _var_var_0
                112     JUMP_FORWARD                    5 (to 124)
                114     LOAD_FAST                       4: _var_var_0
                116     LOAD_CONST                      6: 1
                118     BINARY_OP                       16 (<<=)
                122     STORE_FAST                      4: _var_var_0
                124     LOAD_FAST                       4: _var_var_0
                126     LOAD_CONST                      7: 65535
                128     BINARY_OP                       14 (&=)
                132     STORE_FAST                      4: _var_var_0
                134     JUMP_BACKWARD                   28 (to 80)
                136     END_FOR                         
                138     JUMP_BACKWARD                   52 (to 36)
                140     END_FOR                         
                142     LOAD_FAST                       4: _var_var_0
                144     NOP                             
                146     NOP                             
                148     NOP                             
                150     JUMP_FORWARD                    20 (to 192)
                152     CALL                            1
                160     POP_TOP                         
                162     RETURN_VALUE                    
                164     PUSH_EXC_INFO                   
                166     PUSH_NULL                       
                168     LOAD_CONST                      8: '__pyarmor_exit_41399__'
                170     NOP                             
                172     LOAD_CONST                      3: b'<COAddr>\x03\x00\x00\x1a\x8a\x00\x00\x00\x00\x00\x00\x00'
                174     CALL                            1
                182     POP_TOP                         
                184     RERAISE                         0
                186     COPY                            3
                188     POP_EXCEPT                      
                190     RERAISE                         1
                192     PUSH_NULL                       
                194     LOAD_CONST                      8: '__pyarmor_exit_41399__'
                196     LOAD_CONST                      3: b'<COAddr>\x03\x00\x00\x1a\x8a\x00\x00\x00\x00\x00\x00\x00'
                198     BUILD_TUPLE                     1
                200     CALL_FUNCTION_EX                0
                202     POP_TOP                         
                204     RETURN_VALUE                    
            [Exception Table]
                28 to 144 -> 164 [0] 
                164 to 186 -> 186 [1] lasti
        [Code]
            File Name: <frozen changan.changancan>
            Object Name: create_244_command_a05
            Qualified Name: create_244_command_a05
            Arg Count: 5
            Pos Only Arg Count: 0
            KW Only Arg Count: 0
            Stack Size: 11
            Flags: 0x20000003 (CO_OPTIMIZED | CO_NEWLOCALS | CO_PYARMOR_OBFUSCATED)
            [Names]
                'make_can_msg'
                'crc_calculate_crc8'
                'crc16_ccitt_false'
            [Locals+Names]
                'packer'
                'accel'
                'counter'
                'longActive'
                'accTrq'
                '__assert_armored__'
                '_var_var_3'
                '_var_var_4'
            [Constants]
                None
                '__pyarmor_assert_41400__'
                '__pyarmor_enter_41401__'
                b'<COAddr>\x01\x00\x00\x1a\xc8\x01\x00\x00\x00\x00\x00\x00'
                'ACC_ACCTargetAcceleration'
                'ACC_AEBTargetDeceleration'
                -0.0005
                'unknown'
                1
                'ACC_CDDActive'
                0
                'ACC_LDWStatus'
                'ACC_LDWVibrationWarningReq'
                'ACC_LKAStatus'
                'ACC_TextInfoForDriver'
                'ACC_RollingCounter_24E'
                'ACC_CRCCheck_24E'
                'ACC_RollingCounter_25E'
                'ACC_CRCCheck_25E'
                'ADS_RollingCounter_244'
                'ADS_CRCCheck_244'
                'ACC_ACCMode'
                3
                2
                'ACC_AEBActive'
                'ACC_AccTrqReq'
                120
                0.05
                30
                5005
                (
                    'ACC_AccTrqReqActive'
                    'ACC_FCWPreWarning'
                    'ACC_FCWLatentWarning'
                    'ACC_AWBActive'
                    'ACC_AEBCtrlType'
                    'ACC_LatTakeoverReq'
                    'ACC_LngTakeOverReq'
                    'ADS_EOMTOReq'
                    'ACC_HandsOnReq'
                )
                'GW_244'
                7
                8
                15
                54
                '__pyarmor_exit_41402__'
            [Disassembly]
                0       NOP                             
                2       NOP                             
                4       PUSH_NULL                       
                6       LOAD_CONST                      2: '__pyarmor_enter_41401__'
                8       LOAD_CONST                      3: b'<COAddr>\x01\x00\x00\x1a\xc8\x01\x00\x00\x00\x00\x00\x00'
                10      BUILD_TUPLE                     1
                12      CALL_FUNCTION_EX                0
                14      POP_TOP                         
                16      RESUME                          0
                18      NOP                             
                20      NOP                             
                22      NOP                             
                24      NOP                             
                26      NOP                             
                28      BUILD_MAP                       0
                30      LOAD_CONST                      4: 'ACC_ACCTargetAcceleration'
                32      LOAD_FAST                       1: accel
                34      MAP_ADD                         1
                36      LOAD_CONST                      5: 'ACC_AEBTargetDeceleration'
                38      LOAD_CONST                      6: -0.0005
                40      MAP_ADD                         1
                42      LOAD_CONST                      7: 'unknown'
                44      LOAD_CONST                      8: 1
                46      MAP_ADD                         1
                48      LOAD_CONST                      9: 'ACC_CDDActive'
                50      LOAD_FAST                       1: accel
                52      LOAD_CONST                      10: 0
                54      COMPARE_OP                      2 (<)
                58      POP_JUMP_IF_FALSE               2 (to 64)
                60      LOAD_CONST                      8: 1
                62      JUMP_FORWARD                    1 (to 66)
                64      LOAD_CONST                      10: 0
                66      MAP_ADD                         1
                68      LOAD_CONST                      11: 'ACC_LDWStatus'
                70      LOAD_CONST                      10: 0
                72      MAP_ADD                         1
                74      LOAD_CONST                      12: 'ACC_LDWVibrationWarningReq'
                76      LOAD_CONST                      10: 0
                78      MAP_ADD                         1
                80      LOAD_CONST                      13: 'ACC_LKAStatus'
                82      LOAD_CONST                      10: 0
                84      MAP_ADD                         1
                86      LOAD_CONST                      14: 'ACC_TextInfoForDriver'
                88      LOAD_CONST                      10: 0
                90      MAP_ADD                         1
                92      LOAD_CONST                      15: 'ACC_RollingCounter_24E'
                94      LOAD_FAST                       2: counter
                96      MAP_ADD                         1
                98      LOAD_CONST                      16: 'ACC_CRCCheck_24E'
                100     LOAD_CONST                      10: 0
                102     MAP_ADD                         1
                104     LOAD_CONST                      17: 'ACC_RollingCounter_25E'
                106     LOAD_FAST                       2: counter
                108     MAP_ADD                         1
                110     LOAD_CONST                      18: 'ACC_CRCCheck_25E'
                112     LOAD_CONST                      10: 0
                114     MAP_ADD                         1
                116     LOAD_CONST                      19: 'ADS_RollingCounter_244'
                118     LOAD_FAST                       2: counter
                120     MAP_ADD                         1
                122     LOAD_CONST                      20: 'ADS_CRCCheck_244'
                124     LOAD_CONST                      10: 0
                126     MAP_ADD                         1
                128     LOAD_CONST                      21: 'ACC_ACCMode'
                130     LOAD_FAST                       3: longActive
                132     POP_JUMP_IF_FALSE               2 (to 138)
                134     LOAD_CONST                      22: 3
                136     JUMP_FORWARD                    1 (to 140)
                138     LOAD_CONST                      23: 2
                140     MAP_ADD                         1
                142     LOAD_CONST                      24: 'ACC_AEBActive'
                144     LOAD_CONST                      10: 0
                146     MAP_ADD                         1
                148     LOAD_CONST                      25: 'ACC_AccTrqReq'
                150     LOAD_FAST                       1: accel
                152     LOAD_CONST                      10: 0
                154     COMPARE_OP                      68 (>)
                158     POP_JUMP_IF_FALSE               14 (to 188)
                160     LOAD_CONST                      26: 120
                162     LOAD_FAST                       1: accel
                164     LOAD_CONST                      27: 0.05
                166     BINARY_OP                       10 (-)
                170     LOAD_CONST                      27: 0.05
                172     BINARY_OP                       11 (/)
                176     LOAD_CONST                      28: 30
                178     BINARY_OP                       5 (*)
                182     BINARY_OP                       0 (+)
                186     JUMP_FORWARD                    1 (to 190)
                188     LOAD_CONST                      29: 5005
                190     MAP_ADD                         1
                192     LOAD_FAST                       3: longActive
                194     POP_JUMP_IF_FALSE               7 (to 210)
                196     LOAD_FAST                       1: accel
                198     LOAD_CONST                      10: 0
                200     COMPARE_OP                      68 (>)
                204     POP_JUMP_IF_FALSE               2 (to 210)
                206     LOAD_CONST                      8: 1
                208     JUMP_FORWARD                    1 (to 212)
                210     LOAD_CONST                      10: 0
                212     LOAD_CONST                      10: 0
                214     LOAD_CONST                      10: 0
                216     LOAD_CONST                      10: 0
                218     LOAD_CONST                      10: 0
                220     LOAD_CONST                      10: 0
                222     LOAD_CONST                      10: 0
                224     LOAD_CONST                      10: 0
                226     LOAD_CONST                      10: 0
                228     LOAD_CONST                      30: ('ACC_AccTrqReqActive', 'ACC_FCWPreWarning', 'ACC_FCWLatentWarning', 'ACC_AWBActive', 'ACC_AEBCtrlType', 'ACC_LatTakeoverReq', 'ACC_LngTakeOverReq', 'ADS_EOMTOReq', 'ACC_HandsOnReq')
                230     BUILD_CONST_KEY_MAP             9
                232     DICT_UPDATE                     1
                234     STORE_FAST                      6: _var_var_3
                236     LOAD_FAST                       0: packer
                238     LOAD_ATTR                       1: make_can_msg
                258     LOAD_CONST                      31: 'GW_244'
                260     LOAD_CONST                      10: 0
                262     LOAD_FAST                       6: _var_var_3
                264     CALL                            3
                272     LOAD_CONST                      8: 1
                274     BINARY_SUBSCR                   
                278     STORE_FAST                      7: _var_var_4
                280     LOAD_GLOBAL                     3: NULL + crc_calculate_crc8
                290     LOAD_FAST                       7: _var_var_4
                292     LOAD_CONST                      0: None
                294     LOAD_CONST                      32: 7
                296     BINARY_SLICE                    
                298     CALL                            1
                306     LOAD_FAST                       6: _var_var_3
                308     LOAD_CONST                      16: 'ACC_CRCCheck_24E'
                310     STORE_SUBSCR                    
                314     LOAD_GLOBAL                     3: NULL + crc_calculate_crc8
                324     LOAD_FAST                       7: _var_var_4
                326     LOAD_CONST                      33: 8
                328     LOAD_CONST                      34: 15
                330     BINARY_SLICE                    
                332     CALL                            1
                340     LOAD_FAST                       6: _var_var_3
                342     LOAD_CONST                      18: 'ACC_CRCCheck_25E'
                344     STORE_SUBSCR                    
                348     LOAD_FAST                       0: packer
                350     LOAD_ATTR                       1: make_can_msg
                370     LOAD_CONST                      31: 'GW_244'
                372     LOAD_CONST                      10: 0
                374     LOAD_FAST                       6: _var_var_3
                376     CALL                            3
                384     LOAD_CONST                      8: 1
                386     BINARY_SUBSCR                   
                390     STORE_FAST                      7: _var_var_4
                392     LOAD_GLOBAL                     5: NULL + crc16_ccitt_false
                402     LOAD_FAST                       7: _var_var_4
                404     LOAD_CONST                      0: None
                406     LOAD_CONST                      35: 54
                408     BINARY_SLICE                    
                410     CALL                            1
                418     LOAD_FAST                       6: _var_var_3
                420     LOAD_CONST                      20: 'ADS_CRCCheck_244'
                422     STORE_SUBSCR                    
                426     LOAD_FAST                       0: packer
                428     LOAD_ATTR                       1: make_can_msg
                448     LOAD_CONST                      31: 'GW_244'
                450     LOAD_CONST                      10: 0
                452     LOAD_FAST                       6: _var_var_3
                454     CALL                            3
                462     NOP                             
                464     NOP                             
                466     NOP                             
                468     JUMP_FORWARD                    20 (to 510)
                470     CALL                            1
                478     POP_TOP                         
                480     RETURN_VALUE                    
                482     PUSH_EXC_INFO                   
                484     PUSH_NULL                       
                486     LOAD_CONST                      36: '__pyarmor_exit_41402__'
                488     NOP                             
                490     LOAD_CONST                      3: b'<COAddr>\x01\x00\x00\x1a\xc8\x01\x00\x00\x00\x00\x00\x00'
                492     CALL                            1
                500     POP_TOP                         
                502     RERAISE                         0
                504     COPY                            3
                506     POP_EXCEPT                      
                508     RERAISE                         1
                510     PUSH_NULL                       
                512     LOAD_CONST                      36: '__pyarmor_exit_41402__'
                514     LOAD_CONST                      3: b'<COAddr>\x01\x00\x00\x1a\xc8\x01\x00\x00\x00\x00\x00\x00'
                516     BUILD_TUPLE                     1
                518     CALL_FUNCTION_EX                0
                520     POP_TOP                         
                522     RETURN_VALUE                    
            [Exception Table]
                28 to 462 -> 482 [0] 
                482 to 504 -> 504 [1] lasti
        'msg'
        [Code]
            File Name: <frozen changan.changancan>
            Object Name: create_244_command
            Qualified Name: create_244_command
            Arg Count: 7
            Pos Only Arg Count: 0
            KW Only Arg Count: 0
            Stack Size: 10
            Flags: 0x20000003 (CO_OPTIMIZED | CO_NEWLOCALS | CO_PYARMOR_OBFUSCATED)
            [Names]
                'copy'
                'update'
                'make_can_msg'
                'crc_calculate_crc8'
            [Locals+Names]
                'packer'
                'msg'
                'accel'
                'counter'
                'longActive'
                'accTrq'
                'vEgoRaw'
                '__assert_armored__'
                '_var_var_3'
                '_var_var_4'
            [Constants]
                None
                '__pyarmor_assert_41403__'
                '__pyarmor_enter_41404__'
                b'<COAddr>\x01\x00\x00\x1a(\x01\x00\x00\x00\x00\x00\x00'
                0
                1
                3
                2
                (
                    'ACC_ACCTargetAcceleration'
                    'ACC_CDDActive'
                    'ACC_RollingCounter_24E'
                    'ACC_RollingCounter_25E'
                    'ACC_ACCMode'
                    'ACC_AccTrqReq'
                    'ACC_AccTrqReqActive'
                )
                'GW_244'
                7
                'ACC_CRCCheck_24E'
                8
                15
                'ACC_CRCCheck_25E'
                '__pyarmor_exit_41405__'
            [Disassembly]
                0       NOP                             
                2       NOP                             
                4       PUSH_NULL                       
                6       LOAD_CONST                      2: '__pyarmor_enter_41404__'
                8       LOAD_CONST                      3: b'<COAddr>\x01\x00\x00\x1a(\x01\x00\x00\x00\x00\x00\x00'
                10      BUILD_TUPLE                     1
                12      CALL_FUNCTION_EX                0
                14      POP_TOP                         
                16      RESUME                          0
                18      NOP                             
                20      NOP                             
                22      NOP                             
                24      NOP                             
                26      NOP                             
                28      LOAD_FAST                       1: msg
                30      LOAD_ATTR                       1: copy
                50      CALL                            0
                58      STORE_FAST                      8: _var_var_3
                60      LOAD_FAST                       8: _var_var_3
                62      LOAD_ATTR                       3: update
                82      LOAD_FAST                       2: accel
                84      LOAD_FAST                       4: longActive
                86      POP_JUMP_IF_FALSE               7 (to 102)
                88      LOAD_FAST                       2: accel
                90      LOAD_CONST                      4: 0
                92      COMPARE_OP                      2 (<)
                96      POP_JUMP_IF_FALSE               2 (to 102)
                98      LOAD_CONST                      5: 1
                100     JUMP_FORWARD                    1 (to 104)
                102     LOAD_CONST                      4: 0
                104     LOAD_FAST                       3: counter
                106     LOAD_FAST                       3: counter
                108     LOAD_FAST                       4: longActive
                110     POP_JUMP_IF_FALSE               2 (to 116)
                112     LOAD_CONST                      6: 3
                114     JUMP_FORWARD                    1 (to 118)
                116     LOAD_CONST                      7: 2
                118     LOAD_FAST                       5: accTrq
                120     LOAD_FAST                       4: longActive
                122     POP_JUMP_IF_FALSE               7 (to 138)
                124     LOAD_FAST                       2: accel
                126     LOAD_CONST                      4: 0
                128     COMPARE_OP                      92 (>=)
                132     POP_JUMP_IF_FALSE               2 (to 138)
                134     LOAD_CONST                      5: 1
                136     JUMP_FORWARD                    1 (to 140)
                138     LOAD_CONST                      4: 0
                140     LOAD_CONST                      8: ('ACC_ACCTargetAcceleration', 'ACC_CDDActive', 'ACC_RollingCounter_24E', 'ACC_RollingCounter_25E', 'ACC_ACCMode', 'ACC_AccTrqReq', 'ACC_AccTrqReqActive')
                142     BUILD_CONST_KEY_MAP             7
                144     CALL                            1
                152     POP_TOP                         
                154     LOAD_FAST                       0: packer
                156     LOAD_ATTR                       5: make_can_msg
                176     LOAD_CONST                      9: 'GW_244'
                178     LOAD_CONST                      4: 0
                180     LOAD_FAST                       8: _var_var_3
                182     CALL                            3
                190     LOAD_CONST                      5: 1
                192     BINARY_SUBSCR                   
                196     STORE_FAST                      9: _var_var_4
                198     LOAD_GLOBAL                     7: NULL + crc_calculate_crc8
                208     LOAD_FAST                       9: _var_var_4
                210     LOAD_CONST                      0: None
                212     LOAD_CONST                      10: 7
                214     BINARY_SLICE                    
                216     CALL                            1
                224     LOAD_FAST                       8: _var_var_3
                226     LOAD_CONST                      11: 'ACC_CRCCheck_24E'
                228     STORE_SUBSCR                    
                232     LOAD_GLOBAL                     7: NULL + crc_calculate_crc8
                242     LOAD_FAST                       9: _var_var_4
                244     LOAD_CONST                      12: 8
                246     LOAD_CONST                      13: 15
                248     BINARY_SLICE                    
                250     CALL                            1
                258     LOAD_FAST                       8: _var_var_3
                260     LOAD_CONST                      14: 'ACC_CRCCheck_25E'
                262     STORE_SUBSCR                    
                266     LOAD_FAST                       0: packer
                268     LOAD_ATTR                       5: make_can_msg
                288     LOAD_CONST                      9: 'GW_244'
                290     LOAD_CONST                      4: 0
                292     LOAD_FAST                       8: _var_var_3
                294     CALL                            3
                302     NOP                             
                304     NOP                             
                306     NOP                             
                308     JUMP_FORWARD                    20 (to 350)
                310     CALL                            1
                318     POP_TOP                         
                320     RETURN_VALUE                    
                322     PUSH_EXC_INFO                   
                324     PUSH_NULL                       
                326     LOAD_CONST                      15: '__pyarmor_exit_41405__'
                328     NOP                             
                330     LOAD_CONST                      3: b'<COAddr>\x01\x00\x00\x1a(\x01\x00\x00\x00\x00\x00\x00'
                332     CALL                            1
                340     POP_TOP                         
                342     RERAISE                         0
                344     COPY                            3
                346     POP_EXCEPT                      
                348     RERAISE                         1
                350     PUSH_NULL                       
                352     LOAD_CONST                      15: '__pyarmor_exit_41405__'
                354     LOAD_CONST                      3: b'<COAddr>\x01\x00\x00\x1a(\x01\x00\x00\x00\x00\x00\x00'
                356     BUILD_TUPLE                     1
                358     CALL_FUNCTION_EX                0
                360     POP_TOP                         
                362     RETURN_VALUE                    
            [Exception Table]
                28 to 302 -> 322 [0] 
                322 to 344 -> 344 [1] lasti
        [Code]
            File Name: <frozen changan.changancan>
            Object Name: create_244_command_idd
            Qualified Name: create_244_command_idd
            Arg Count: 7
            Pos Only Arg Count: 0
            KW Only Arg Count: 0
            Stack Size: 6
            Flags: 0x20000003 (CO_OPTIMIZED | CO_NEWLOCALS | CO_PYARMOR_OBFUSCATED)
            [Names]
                'copy'
                'update'
                'make_can_msg'
                'crc_calculate_crc8'
            [Locals+Names]
                'packer'
                'msg'
                'accel'
                'counter'
                'longActive'
                'accTrq'
                'vEgoRaw'
                '__assert_armored__'
                '_var_var_3'
                '_var_var_4'
            [Constants]
                None
                '__pyarmor_assert_41406__'
                '__pyarmor_enter_41407__'
                b'<COAddr>\x03\x00\x00\x1a\x9a\x01\x00\x00\x00\x00\x00\x00'
                'ACC_ACCTargetAcceleration'
                'ACC_CDDActive'
                0
                1
                'ACC_RollingCounter_24E'
                'ACC_RollingCounter_25E'
                'ACC_ACCMode'
                3
                2
                'ACC_AccTrqReq'
                'ACC_AccTrqReqActive'
                'ACC_DecToStop'
                'ACC_AWBActive'
                'ACC_AEBCtrlType'
                'ACC_TextInfoForDriver'
                'ACC_Driveoff_Request'
                'ACC_FCWPreWarning'
                'ACC_FCWLatentWarning'
                'ACC_LatTakeoverReq'
                'ACC_LngTakeOverReq'
                'ACC_HandsOnReq'
                'GW_244'
                7
                'ACC_CRCCheck_24E'
                8
                15
                'ACC_CRCCheck_25E'
                '__pyarmor_exit_41408__'
            [Disassembly]
                0       NOP                             
                2       NOP                             
                4       PUSH_NULL                       
                6       LOAD_CONST                      2: '__pyarmor_enter_41407__'
                8       LOAD_CONST                      3: b'<COAddr>\x03\x00\x00\x1a\x9a\x01\x00\x00\x00\x00\x00\x00'
                10      BUILD_TUPLE                     1
                12      CALL_FUNCTION_EX                0
                14      POP_TOP                         
                16      RESUME                          0
                18      NOP                             
                20      NOP                             
                22      NOP                             
                24      NOP                             
                26      NOP                             
                28      LOAD_FAST                       1: msg
                30      LOAD_ATTR                       1: copy
                50      CALL                            0
                58      STORE_FAST                      8: _var_var_3
                60      LOAD_FAST                       8: _var_var_3
                62      LOAD_ATTR                       3: update
                82      BUILD_MAP                       0
                84      LOAD_CONST                      4: 'ACC_ACCTargetAcceleration'
                86      LOAD_FAST                       2: accel
                88      MAP_ADD                         1
                90      LOAD_CONST                      5: 'ACC_CDDActive'
                92      LOAD_FAST                       4: longActive
                94      POP_JUMP_IF_FALSE               7 (to 110)
                96      LOAD_FAST                       2: accel
                98      LOAD_CONST                      6: 0
                100     COMPARE_OP                      2 (<)
                104     POP_JUMP_IF_FALSE               2 (to 110)
                106     LOAD_CONST                      7: 1
                108     JUMP_FORWARD                    1 (to 112)
                110     LOAD_CONST                      6: 0
                112     MAP_ADD                         1
                114     LOAD_CONST                      8: 'ACC_RollingCounter_24E'
                116     LOAD_FAST                       3: counter
                118     MAP_ADD                         1
                120     LOAD_CONST                      9: 'ACC_RollingCounter_25E'
                122     LOAD_FAST                       3: counter
                124     MAP_ADD                         1
                126     LOAD_CONST                      10: 'ACC_ACCMode'
                128     LOAD_FAST                       4: longActive
                130     POP_JUMP_IF_FALSE               2 (to 136)
                132     LOAD_CONST                      11: 3
                134     JUMP_FORWARD                    1 (to 138)
                136     LOAD_CONST                      12: 2
                138     MAP_ADD                         1
                140     LOAD_CONST                      13: 'ACC_AccTrqReq'
                142     LOAD_FAST                       5: accTrq
                144     MAP_ADD                         1
                146     LOAD_CONST                      14: 'ACC_AccTrqReqActive'
                148     LOAD_FAST                       4: longActive
                150     POP_JUMP_IF_FALSE               7 (to 166)
                152     LOAD_FAST                       2: accel
                154     LOAD_CONST                      6: 0
                156     COMPARE_OP                      92 (>=)
                160     POP_JUMP_IF_FALSE               2 (to 166)
                162     LOAD_CONST                      7: 1
                164     JUMP_FORWARD                    1 (to 168)
                166     LOAD_CONST                      6: 0
                168     MAP_ADD                         1
                170     LOAD_CONST                      15: 'ACC_DecToStop'
                172     LOAD_FAST                       4: longActive
                174     POP_JUMP_IF_FALSE               12 (to 200)
                176     LOAD_FAST                       2: accel
                178     LOAD_CONST                      6: 0
                180     COMPARE_OP                      2 (<)
                184     POP_JUMP_IF_FALSE               7 (to 200)
                186     LOAD_FAST                       6: vEgoRaw
                188     LOAD_CONST                      6: 0
                190     COMPARE_OP                      40 (==)
                194     POP_JUMP_IF_FALSE               2 (to 200)
                196     LOAD_CONST                      7: 1
                198     JUMP_FORWARD                    1 (to 202)
                200     LOAD_CONST                      6: 0
                202     MAP_ADD                         1
                204     LOAD_CONST                      16: 'ACC_AWBActive'
                206     LOAD_CONST                      6: 0
                208     MAP_ADD                         1
                210     LOAD_CONST                      17: 'ACC_AEBCtrlType'
                212     LOAD_CONST                      6: 0
                214     MAP_ADD                         1
                216     LOAD_CONST                      18: 'ACC_TextInfoForDriver'
                218     LOAD_CONST                      6: 0
                220     MAP_ADD                         1
                222     LOAD_CONST                      19: 'ACC_Driveoff_Request'
                224     LOAD_CONST                      6: 0
                226     MAP_ADD                         1
                228     LOAD_CONST                      20: 'ACC_FCWPreWarning'
                230     LOAD_CONST                      6: 0
                232     MAP_ADD                         1
                234     LOAD_CONST                      21: 'ACC_FCWLatentWarning'
                236     LOAD_CONST                      6: 0
                238     MAP_ADD                         1
                240     LOAD_CONST                      22: 'ACC_LatTakeoverReq'
                242     LOAD_CONST                      6: 0
                244     MAP_ADD                         1
                246     LOAD_CONST                      23: 'ACC_LngTakeOverReq'
                248     LOAD_CONST                      6: 0
                250     MAP_ADD                         1
                252     LOAD_CONST                      24: 'ACC_HandsOnReq'
                254     LOAD_CONST                      6: 0
                256     MAP_ADD                         1
                258     CALL                            1
                266     POP_TOP                         
                268     LOAD_FAST                       0: packer
                270     LOAD_ATTR                       5: make_can_msg
                290     LOAD_CONST                      25: 'GW_244'
                292     LOAD_CONST                      6: 0
                294     LOAD_FAST                       8: _var_var_3
                296     CALL                            3
                304     LOAD_CONST                      7: 1
                306     BINARY_SUBSCR                   
                310     STORE_FAST                      9: _var_var_4
                312     LOAD_GLOBAL                     7: NULL + crc_calculate_crc8
                322     LOAD_FAST                       9: _var_var_4
                324     LOAD_CONST                      0: None
                326     LOAD_CONST                      26: 7
                328     BINARY_SLICE                    
                330     CALL                            1
                338     LOAD_FAST                       8: _var_var_3
                340     LOAD_CONST                      27: 'ACC_CRCCheck_24E'
                342     STORE_SUBSCR                    
                346     LOAD_GLOBAL                     7: NULL + crc_calculate_crc8
                356     LOAD_FAST                       9: _var_var_4
                358     LOAD_CONST                      28: 8
                360     LOAD_CONST                      29: 15
                362     BINARY_SLICE                    
                364     CALL                            1
                372     LOAD_FAST                       8: _var_var_3
                374     LOAD_CONST                      30: 'ACC_CRCCheck_25E'
                376     STORE_SUBSCR                    
                380     LOAD_FAST                       0: packer
                382     LOAD_ATTR                       5: make_can_msg
                402     LOAD_CONST                      25: 'GW_244'
                404     LOAD_CONST                      6: 0
                406     LOAD_FAST                       8: _var_var_3
                408     CALL                            3
                416     NOP                             
                418     NOP                             
                420     NOP                             
                422     JUMP_FORWARD                    20 (to 464)
                424     CALL                            1
                432     POP_TOP                         
                434     RETURN_VALUE                    
                436     PUSH_EXC_INFO                   
                438     PUSH_NULL                       
                440     LOAD_CONST                      31: '__pyarmor_exit_41408__'
                442     NOP                             
                444     LOAD_CONST                      3: b'<COAddr>\x03\x00\x00\x1a\x9a\x01\x00\x00\x00\x00\x00\x00'
                446     CALL                            1
                454     POP_TOP                         
                456     RERAISE                         0
                458     COPY                            3
                460     POP_EXCEPT                      
                462     RERAISE                         1
                464     PUSH_NULL                       
                466     LOAD_CONST                      31: '__pyarmor_exit_41408__'
                468     LOAD_CONST                      3: b'<COAddr>\x03\x00\x00\x1a\x9a\x01\x00\x00\x00\x00\x00\x00'
                470     BUILD_TUPLE                     1
                472     CALL_FUNCTION_EX                0
                474     POP_TOP                         
                476     RETURN_VALUE                    
            [Exception Table]
                28 to 416 -> 436 [0] 
                436 to 458 -> 458 [1] lasti
        [Code]
            File Name: <frozen changan.changancan>
            Object Name: create_1BA_command
            Qualified Name: create_1BA_command
            Arg Count: 5
            Pos Only Arg Count: 0
            KW Only Arg Count: 0
            Stack Size: 6
            Flags: 0x20000003 (CO_OPTIMIZED | CO_NEWLOCALS | CO_PYARMOR_OBFUSCATED)
            [Names]
                'update'
                'make_can_msg'
                'crc_calculate_crc8'
            [Locals+Names]
                'packer'
                'msg'
                'angle'
                'latCtrlActive'
                'counter'
                '__assert_armored__'
                '_var_var_5'
                '_var_var_3'
                '_var_var_4'
            [Constants]
                None
                '__pyarmor_assert_41409__'
                '__pyarmor_enter_41410__'
                b'<COAddr>\x01\x00\x00\x1a\xe2\x00\x00\x00\x00\x00\x00\x00'
                (
                    'ACC_CRCCheck_1BA'
                    'ACC_RollingCounter_1BA'
                    'EPS_LatCtrlActive'
                    'EPS_AngleCmd'
                    'ACC_MotorTorqueMinLimitRequest'
                    'ACC_MotorTorqueMaxLimitRequest'
                )
                (
                    'EPS_AngleCmd'
                    'EPS_LatCtrlActive'
                    'ACC_RollingCounter_1BA'
                )
                'GW_1BA'
                0
                1
                7
                'ACC_CRCCheck_1BA'
                '__pyarmor_exit_41411__'
            [Disassembly]
                0       NOP                             
                2       NOP                             
                4       PUSH_NULL                       
                6       LOAD_CONST                      2: '__pyarmor_enter_41410__'
                8       LOAD_CONST                      3: b'<COAddr>\x01\x00\x00\x1a\xe2\x00\x00\x00\x00\x00\x00\x00'
                10      BUILD_TUPLE                     1
                12      CALL_FUNCTION_EX                0
                14      POP_TOP                         
                16      RESUME                          0
                18      NOP                             
                20      NOP                             
                22      NOP                             
                24      NOP                             
                26      NOP                             
                28      LOAD_CONST                      4: ('ACC_CRCCheck_1BA', 'ACC_RollingCounter_1BA', 'EPS_LatCtrlActive', 'EPS_AngleCmd', 'ACC_MotorTorqueMinLimitRequest', 'ACC_MotorTorqueMaxLimitRequest')
                30      GET_ITER                        
                32      LOAD_FAST_AND_CLEAR             6: _var_var_5
                34      SWAP                            2
                36      BUILD_MAP                       0
                38      SWAP                            2
                40      FOR_ITER                        8 (to 58)
                44      STORE_FAST                      6: _var_var_5
                46      LOAD_FAST                       6: _var_var_5
                48      LOAD_FAST                       1: msg
                50      LOAD_FAST                       6: _var_var_5
                52      BINARY_SUBSCR                   
                56      MAP_ADD                         2
                58      JUMP_BACKWARD                   10 (to 40)
                60      END_FOR                         
                62      STORE_FAST                      7: _var_var_3
                64      STORE_FAST                      6: _var_var_5
                66      LOAD_FAST                       7: _var_var_3
                68      LOAD_ATTR                       1: update
                88      LOAD_FAST                       2: angle
                90      LOAD_FAST                       3: latCtrlActive
                92      LOAD_FAST                       4: counter
                94      LOAD_CONST                      5: ('EPS_AngleCmd', 'EPS_LatCtrlActive', 'ACC_RollingCounter_1BA')
                96      BUILD_CONST_KEY_MAP             3
                98      CALL                            1
                106     POP_TOP                         
                108     LOAD_FAST                       0: packer
                110     LOAD_ATTR                       3: make_can_msg
                130     LOAD_CONST                      6: 'GW_1BA'
                132     LOAD_CONST                      7: 0
                134     LOAD_FAST                       7: _var_var_3
                136     CALL                            3
                144     LOAD_CONST                      8: 1
                146     BINARY_SUBSCR                   
                150     STORE_FAST                      8: _var_var_4
                152     LOAD_GLOBAL                     5: NULL + crc_calculate_crc8
                162     LOAD_FAST                       8: _var_var_4
                164     LOAD_CONST                      0: None
                166     LOAD_CONST                      9: 7
                168     BINARY_SLICE                    
                170     CALL                            1
                178     LOAD_FAST                       7: _var_var_3
                180     LOAD_CONST                      10: 'ACC_CRCCheck_1BA'
                182     STORE_SUBSCR                    
                186     LOAD_FAST                       0: packer
                188     LOAD_ATTR                       3: make_can_msg
                208     LOAD_CONST                      6: 'GW_1BA'
                210     LOAD_CONST                      7: 0
                212     LOAD_FAST                       7: _var_var_3
                214     CALL                            3
                222     NOP                             
                224     NOP                             
                226     NOP                             
                228     JUMP_FORWARD                    25 (to 280)
                230     CALL                            1
                238     POP_TOP                         
                240     RETURN_VALUE                    
                242     SWAP                            2
                244     POP_TOP                         
                246     SWAP                            2
                248     STORE_FAST                      6: _var_var_5
                250     RERAISE                         0
                252     PUSH_EXC_INFO                   
                254     PUSH_NULL                       
                256     LOAD_CONST                      11: '__pyarmor_exit_41411__'
                258     NOP                             
                260     LOAD_CONST                      3: b'<COAddr>\x01\x00\x00\x1a\xe2\x00\x00\x00\x00\x00\x00\x00'
                262     CALL                            1
                270     POP_TOP                         
                272     RERAISE                         0
                274     COPY                            3
                276     POP_EXCEPT                      
                278     RERAISE                         1
                280     PUSH_NULL                       
                282     LOAD_CONST                      11: '__pyarmor_exit_41411__'
                284     LOAD_CONST                      3: b'<COAddr>\x01\x00\x00\x1a\xe2\x00\x00\x00\x00\x00\x00\x00'
                286     BUILD_TUPLE                     1
                288     CALL_FUNCTION_EX                0
                290     POP_TOP                         
                292     RETURN_VALUE                    
            [Exception Table]
                28 to 36 -> 252 [0] 
                36 to 62 -> 242 [2] 
                62 to 222 -> 252 [0] 
                242 to 252 -> 252 [0] 
                252 to 274 -> 274 [1] lasti
        [Code]
            File Name: <frozen changan.changancan>
            Object Name: create_17E_command
            Qualified Name: create_17E_command
            Arg Count: 4
            Pos Only Arg Count: 0
            KW Only Arg Count: 0
            Stack Size: 6
            Flags: 0x20000003 (CO_OPTIMIZED | CO_NEWLOCALS | CO_PYARMOR_OBFUSCATED)
            [Names]
                'update'
                'make_can_msg'
                'crc_calculate_crc8'
            [Locals+Names]
                'packer'
                'msg'
                'longActive'
                'counter'
                '__assert_armored__'
                '_var_var_5'
                '_var_var_3'
                '_var_var_4'
            [Constants]
                None
                '__pyarmor_assert_41412__'
                '__pyarmor_enter_41413__'
                b'<COAddr>\x03\x00\x00\x1a\xfa\x00\x00\x00\x00\x00\x00\x00'
                (
                    'EPS_CRCCheck_17E'
                    'EPS_RollingCounter_17E'
                    'EPS_LatCtrlAvailabilityStatus'
                    'EPS_LatCtrlActive'
                    'EPS_Handwheel_Relang_Valid'
                    'EPS_MeasuredTorsionBarTorqValid'
                    'EPS_Handwheel_Relang'
                    'EPS_Pinionang'
                    'EPS_Pinionang_Valid'
                    'EPS_ADS_Abortfeedback'
                    'EPS_MeasuredTorsionBarTorque'
                )
                'EPS_MeasuredTorsionBarTorque'
                1
                (
                    'EPS_MeasuredTorsionBarTorque'
                    'EPS_RollingCounter_17E'
                )
                'GW_17E'
                0
                7
                'EPS_CRCCheck_17E'
                2
                '__pyarmor_exit_41414__'
            [Disassembly]
                0       NOP                             
                2       NOP                             
                4       PUSH_NULL                       
                6       LOAD_CONST                      2: '__pyarmor_enter_41413__'
                8       LOAD_CONST                      3: b'<COAddr>\x03\x00\x00\x1a\xfa\x00\x00\x00\x00\x00\x00\x00'
                10      BUILD_TUPLE                     1
                12      CALL_FUNCTION_EX                0
                14      POP_TOP                         
                16      RESUME                          0
                18      NOP                             
                20      NOP                             
                22      NOP                             
                24      NOP                             
                26      NOP                             
                28      LOAD_CONST                      4: ('EPS_CRCCheck_17E', 'EPS_RollingCounter_17E', 'EPS_LatCtrlAvailabilityStatus', 'EPS_LatCtrlActive', 'EPS_Handwheel_Relang_Valid', 'EPS_MeasuredTorsionBarTorqValid', 'EPS_Handwheel_Relang', 'EPS_Pinionang', 'EPS_Pinionang_Valid', 'EPS_ADS_Abortfeedback', 'EPS_MeasuredTorsionBarTorque')
                30      GET_ITER                        
                32      LOAD_FAST_AND_CLEAR             5: _var_var_5
                34      SWAP                            2
                36      BUILD_MAP                       0
                38      SWAP                            2
                40      FOR_ITER                        8 (to 58)
                44      STORE_FAST                      5: _var_var_5
                46      LOAD_FAST                       5: _var_var_5
                48      LOAD_FAST                       1: msg
                50      LOAD_FAST                       5: _var_var_5
                52      BINARY_SUBSCR                   
                56      MAP_ADD                         2
                58      JUMP_BACKWARD                   10 (to 40)
                60      END_FOR                         
                62      STORE_FAST                      6: _var_var_3
                64      STORE_FAST                      5: _var_var_5
                66      LOAD_FAST                       6: _var_var_3
                68      LOAD_ATTR                       1: update
                88      LOAD_FAST                       2: longActive
                90      POP_JUMP_IF_FALSE               8 (to 108)
                92      LOAD_FAST                       1: msg
                94      LOAD_CONST                      5: 'EPS_MeasuredTorsionBarTorque'
                96      BINARY_SUBSCR                   
                100     LOAD_CONST                      6: 1
                102     BINARY_OP                       0 (+)
                106     JUMP_FORWARD                    4 (to 116)
                108     LOAD_FAST                       1: msg
                110     LOAD_CONST                      5: 'EPS_MeasuredTorsionBarTorque'
                112     BINARY_SUBSCR                   
                116     LOAD_FAST                       3: counter
                118     LOAD_CONST                      7: ('EPS_MeasuredTorsionBarTorque', 'EPS_RollingCounter_17E')
                120     BUILD_CONST_KEY_MAP             2
                122     CALL                            1
                130     POP_TOP                         
                132     LOAD_FAST                       0: packer
                134     LOAD_ATTR                       3: make_can_msg
                154     LOAD_CONST                      8: 'GW_17E'
                156     LOAD_CONST                      9: 0
                158     LOAD_FAST                       6: _var_var_3
                160     CALL                            3
                168     LOAD_CONST                      6: 1
                170     BINARY_SUBSCR                   
                174     STORE_FAST                      7: _var_var_4
                176     LOAD_GLOBAL                     5: NULL + crc_calculate_crc8
                186     LOAD_FAST                       7: _var_var_4
                188     LOAD_CONST                      0: None
                190     LOAD_CONST                      10: 7
                192     BINARY_SLICE                    
                194     CALL                            1
                202     LOAD_FAST                       6: _var_var_3
                204     LOAD_CONST                      11: 'EPS_CRCCheck_17E'
                206     STORE_SUBSCR                    
                210     LOAD_FAST                       0: packer
                212     LOAD_ATTR                       3: make_can_msg
                232     LOAD_CONST                      8: 'GW_17E'
                234     LOAD_CONST                      12: 2
                236     LOAD_FAST                       6: _var_var_3
                238     CALL                            3
                246     NOP                             
                248     NOP                             
                250     NOP                             
                252     JUMP_FORWARD                    25 (to 304)
                254     CALL                            1
                262     POP_TOP                         
                264     RETURN_VALUE                    
                266     SWAP                            2
                268     POP_TOP                         
                270     SWAP                            2
                272     STORE_FAST                      5: _var_var_5
                274     RERAISE                         0
                276     PUSH_EXC_INFO                   
                278     PUSH_NULL                       
                280     LOAD_CONST                      13: '__pyarmor_exit_41414__'
                282     NOP                             
                284     LOAD_CONST                      3: b'<COAddr>\x03\x00\x00\x1a\xfa\x00\x00\x00\x00\x00\x00\x00'
                286     CALL                            1
                294     POP_TOP                         
                296     RERAISE                         0
                298     COPY                            3
                300     POP_EXCEPT                      
                302     RERAISE                         1
                304     PUSH_NULL                       
                306     LOAD_CONST                      13: '__pyarmor_exit_41414__'
                308     LOAD_CONST                      3: b'<COAddr>\x03\x00\x00\x1a\xfa\x00\x00\x00\x00\x00\x00\x00'
                310     BUILD_TUPLE                     1
                312     CALL_FUNCTION_EX                0
                314     POP_TOP                         
                316     RETURN_VALUE                    
            [Exception Table]
                28 to 36 -> 276 [0] 
                36 to 62 -> 266 [2] 
                62 to 246 -> 276 [0] 
                266 to 276 -> 276 [0] 
                276 to 298 -> 298 [1] lasti
        [Code]
            File Name: <frozen changan.changancan>
            Object Name: create_307_command
            Qualified Name: create_307_command
            Arg Count: 4
            Pos Only Arg Count: 0
            KW Only Arg Count: 0
            Stack Size: 8
            Flags: 0x20000003 (CO_OPTIMIZED | CO_NEWLOCALS | CO_PYARMOR_OBFUSCATED)
            [Names]
                'update'
                'make_can_msg'
                'crc_calculate_crc8'
            [Locals+Names]
                'packer'
                'msg'
                'counter'
                'cruiseSpeed'
                '__assert_armored__'
                '_var_var_5'
                '_var_var_3'
                '_var_var_4'
            [Constants]
                None
                '__pyarmor_assert_41415__'
                '__pyarmor_enter_41416__'
                b'<COAddr>\x01\x00\x00\x1aL\x01\x00\x00\x00\x00\x00\x00'
                (
                    'ACC_RLaneDistanceFus'
                    'ACC_LLaneDistanceFus'
                    'ACC_RRLaneDis'
                    'ACC_LLLaneDis'
                    'ACC_Target7ZoneID'
                    'ACC_Target7HeadingAngle'
                    'ACC_Target7LatRange'
                    'ACC_Target7LngRange'
                    'ACC_Target7Direction'
                    'ACC_Target7Type'
                    'ACC_Target7ID'
                    'ACC_Target7Detection'
                    'ACC_Target6ZoneID'
                    'ACC_Target6HeadingAngle'
                    'ACC_Target6LatRange'
                    'ACC_Target6LngRange'
                    'ACC_Target6Direction'
                    'ACC_Target6Type'
                    'ACC_Target6ID'
                    'ACC_Target6Detection'
                    'ACC_CRCCheck_35F'
                    'ACC_RollingCounter_35F'
                    'ACC_CSLAEnableStatus'
                    'ACC_IACCProhibitionTime'
                    'ACC_CSLSetReq'
                    'ACC_VehicleStartRemindSts'
                    'ACC_CRCCheck_344'
                    'ACC_RollingCounter_344'
                    'ACC_CRCCheck_322'
                    'ACC_RollingCounter_322'
                    'ACC_ACCTargetRelSpd'
                    'ACC_FRadarCalibrationStatus'
                    'ACC_CRCCheck_35E'
                    'ACC_RollingCounter_35E'
                    'ACC_AEBEnable'
                    'ACC_FCWSettingStatus'
                    'ACC_TimeGapSet'
                    'ACC_DistanceLevel'
                    'ACC_ObjValid'
                    'ACC_SetSpeed'
                )
                (
                    'ACC_SetSpeed'
                    'ACC_RollingCounter_35E'
                    'ACC_RollingCounter_322'
                    'ACC_RollingCounter_344'
                    'ACC_RollingCounter_35F'
                )
                'GW_307'
                0
                1
                7
                'ACC_CRCCheck_35E'
                8
                15
                'ACC_CRCCheck_322'
                16
                23
                'ACC_CRCCheck_344'
                24
                31
                'ACC_CRCCheck_35F'
                '__pyarmor_exit_41417__'
            [Disassembly]
                0       NOP                             
                2       NOP                             
                4       PUSH_NULL                       
                6       LOAD_CONST                      2: '__pyarmor_enter_41416__'
                8       LOAD_CONST                      3: b'<COAddr>\x01\x00\x00\x1aL\x01\x00\x00\x00\x00\x00\x00'
                10      BUILD_TUPLE                     1
                12      CALL_FUNCTION_EX                0
                14      POP_TOP                         
                16      RESUME                          0
                18      NOP                             
                20      NOP                             
                22      NOP                             
                24      NOP                             
                26      NOP                             
                28      LOAD_CONST                      4: ('ACC_RLaneDistanceFus', 'ACC_LLaneDistanceFus', 'ACC_RRLaneDis', 'ACC_LLLaneDis', 'ACC_Target7ZoneID', 'ACC_Target7HeadingAngle', 'ACC_Target7LatRange', 'ACC_Target7LngRange', 'ACC_Target7Direction', 'ACC_Target7Type', 'ACC_Target7ID', 'ACC_Target7Detection', 'ACC_Target6ZoneID', 'ACC_Target6HeadingAngle', 'ACC_Target6LatRange', 'ACC_Target6LngRange', 'ACC_Target6Direction', 'ACC_Target6Type', 'ACC_Target6ID', 'ACC_Target6Detection', 'ACC_CRCCheck_35F', 'ACC_RollingCounter_35F', 'ACC_CSLAEnableStatus', 'ACC_IACCProhibitionTime', 'ACC_CSLSetReq', 'ACC_VehicleStartRemindSts', 'ACC_CRCCheck_344', 'ACC_RollingCounter_344', 'ACC_CRCCheck_322', 'ACC_RollingCounter_322', 'ACC_ACCTargetRelSpd', 'ACC_FRadarCalibrationStatus', 'ACC_CRCCheck_35E', 'ACC_RollingCounter_35E', 'ACC_AEBEnable', 'ACC_FCWSettingStatus', 'ACC_TimeGapSet', 'ACC_DistanceLevel', 'ACC_ObjValid', 'ACC_SetSpeed')
                30      GET_ITER                        
                32      LOAD_FAST_AND_CLEAR             5: _var_var_5
                34      SWAP                            2
                36      BUILD_MAP                       0
                38      SWAP                            2
                40      FOR_ITER                        8 (to 58)
                44      STORE_FAST                      5: _var_var_5
                46      LOAD_FAST                       5: _var_var_5
                48      LOAD_FAST                       1: msg
                50      LOAD_FAST                       5: _var_var_5
                52      BINARY_SUBSCR                   
                56      MAP_ADD                         2
                58      JUMP_BACKWARD                   10 (to 40)
                60      END_FOR                         
                62      STORE_FAST                      6: _var_var_3
                64      STORE_FAST                      5: _var_var_5
                66      LOAD_FAST                       6: _var_var_3
                68      LOAD_ATTR                       1: update
                88      LOAD_FAST                       3: cruiseSpeed
                90      LOAD_FAST                       2: counter
                92      LOAD_FAST                       2: counter
                94      LOAD_FAST                       2: counter
                96      LOAD_FAST                       2: counter
                98      LOAD_CONST                      5: ('ACC_SetSpeed', 'ACC_RollingCounter_35E', 'ACC_RollingCounter_322', 'ACC_RollingCounter_344', 'ACC_RollingCounter_35F')
                100     BUILD_CONST_KEY_MAP             5
                102     CALL                            1
                110     POP_TOP                         
                112     LOAD_FAST                       0: packer
                114     LOAD_ATTR                       3: make_can_msg
                134     LOAD_CONST                      6: 'GW_307'
                136     LOAD_CONST                      7: 0
                138     LOAD_FAST                       6: _var_var_3
                140     CALL                            3
                148     LOAD_CONST                      8: 1
                150     BINARY_SUBSCR                   
                154     STORE_FAST                      7: _var_var_4
                156     LOAD_GLOBAL                     5: NULL + crc_calculate_crc8
                166     LOAD_FAST                       7: _var_var_4
                168     LOAD_CONST                      0: None
                170     LOAD_CONST                      9: 7
                172     BINARY_SLICE                    
                174     CALL                            1
                182     LOAD_FAST                       6: _var_var_3
                184     LOAD_CONST                      10: 'ACC_CRCCheck_35E'
                186     STORE_SUBSCR                    
                190     LOAD_GLOBAL                     5: NULL + crc_calculate_crc8
                200     LOAD_FAST                       7: _var_var_4
                202     LOAD_CONST                      11: 8
                204     LOAD_CONST                      12: 15
                206     BINARY_SLICE                    
                208     CALL                            1
                216     LOAD_FAST                       6: _var_var_3
                218     LOAD_CONST                      13: 'ACC_CRCCheck_322'
                220     STORE_SUBSCR                    
                224     LOAD_GLOBAL                     5: NULL + crc_calculate_crc8
                234     LOAD_FAST                       7: _var_var_4
                236     LOAD_CONST                      14: 16
                238     LOAD_CONST                      15: 23
                240     BINARY_SLICE                    
                242     CALL                            1
                250     LOAD_FAST                       6: _var_var_3
                252     LOAD_CONST                      16: 'ACC_CRCCheck_344'
                254     STORE_SUBSCR                    
                258     LOAD_GLOBAL                     5: NULL + crc_calculate_crc8
                268     LOAD_FAST                       7: _var_var_4
                270     LOAD_CONST                      17: 24
                272     LOAD_CONST                      18: 31
                274     BINARY_SLICE                    
                276     CALL                            1
                284     LOAD_FAST                       6: _var_var_3
                286     LOAD_CONST                      19: 'ACC_CRCCheck_35F'
                288     STORE_SUBSCR                    
                292     LOAD_FAST                       0: packer
                294     LOAD_ATTR                       3: make_can_msg
                314     LOAD_CONST                      6: 'GW_307'
                316     LOAD_CONST                      7: 0
                318     LOAD_FAST                       6: _var_var_3
                320     CALL                            3
                328     NOP                             
                330     NOP                             
                332     NOP                             
                334     JUMP_FORWARD                    25 (to 386)
                336     CALL                            1
                344     POP_TOP                         
                346     RETURN_VALUE                    
                348     SWAP                            2
                350     POP_TOP                         
                352     SWAP                            2
                354     STORE_FAST                      5: _var_var_5
                356     RERAISE                         0
                358     PUSH_EXC_INFO                   
                360     PUSH_NULL                       
                362     LOAD_CONST                      20: '__pyarmor_exit_41417__'
                364     NOP                             
                366     LOAD_CONST                      3: b'<COAddr>\x01\x00\x00\x1aL\x01\x00\x00\x00\x00\x00\x00'
                368     CALL                            1
                376     POP_TOP                         
                378     RERAISE                         0
                380     COPY                            3
                382     POP_EXCEPT                      
                384     RERAISE                         1
                386     PUSH_NULL                       
                388     LOAD_CONST                      20: '__pyarmor_exit_41417__'
                390     LOAD_CONST                      3: b'<COAddr>\x01\x00\x00\x1aL\x01\x00\x00\x00\x00\x00\x00'
                392     BUILD_TUPLE                     1
                394     CALL_FUNCTION_EX                0
                396     POP_TOP                         
                398     RETURN_VALUE                    
            [Exception Table]
                28 to 36 -> 358 [0] 
                36 to 62 -> 348 [2] 
                62 to 328 -> 358 [0] 
                348 to 358 -> 358 [0] 
                358 to 380 -> 380 [1] lasti
        [Code]
            File Name: <frozen changan.changancan>
            Object Name: create_31A_command
            Qualified Name: create_31A_command
            Arg Count: 5
            Pos Only Arg Count: 0
            KW Only Arg Count: 0
            Stack Size: 12
            Flags: 0x20000003 (CO_OPTIMIZED | CO_NEWLOCALS | CO_PYARMOR_OBFUSCATED)
            [Names]
                'update'
                'make_can_msg'
                'crc_calculate_crc8'
            [Locals+Names]
                'packer'
                'msg'
                'counter'
                'longActive'
                'steeringPressed'
                '__assert_armored__'
                '_var_var_5'
                '_var_var_3'
                '_var_var_6'
                '_var_var_4'
            [Constants]
                None
                '__pyarmor_assert_41418__'
                '__pyarmor_enter_41419__'
                b'<COAddr>\x01\x00\x00\x1av\x01\x00\x00\x00\x00\x00\x00'
                (
                    'ACC_CRCCheck_367'
                    'ACC_RollingCounter_367'
                    'ACC_LatPathHeadingAngle'
                    'ACC_LatPathDY'
                    'ACC_ELKEnableStatus'
                    'ACC_ELKInterventionMode'
                    'ACC_ELKMode'
                    'ACC_CRCCheck_30D'
                    'ACC_RollingCounter_30D'
                    'ACC_HighBeamControl'
                    'ACC_RRLaneDetection'
                    'ACC_LLLaneDetection'
                    'ACC_TargetBasedLateralControl'
                    'ACC_DriverHandsOffStatus'
                    'ACC_IACCHWATextInfoForDriver'
                    'ACC_IACCHWAMode'
                    'ACC_CRCCheck_30A'
                    'ACC_RollingCounter_30A'
                    'ACC_LaneChangeStatus'
                    'ACC_RoadCurvatureFar'
                    'ACC_RoadCurvatureNear'
                    'ACC_RoadCurvature'
                    'ACC_LLaneMarkerType'
                    'ACC_HostLaneLeftStatus'
                    'ACC_HostLaneRightStatus'
                    'ACC_IACCHWAEnable'
                    'ACC_RLaneMarkerType'
                    'ACC_CRCCheck_36D'
                    'ACC_RollingCounter_36D'
                    'ACC_FRadarFailureStatus'
                    'ACC_Voiceinfo'
                    'ACC_AEBTargetmode'
                    'ACC_AEBTextInfo'
                    'ACC_AEBStatus'
                    'ACC_ELKAlert'
                    'ACC_AEBTargetLatRange'
                    'ACC_AEBTargetRelSpeed'
                    'ACC_AEBTargetLngRange'
                )
                1
                4
                3
                2
                0
                (
                    'ACC_IACCHWAMode'
                    'ACC_TargetBasedLateralControl'
                    'ACC_AEBTextInfo'
                    'ACC_IACCHWATextInfoForDriver'
                    'ACC_ELKAlert'
                    'ACC_RollingCounter_36D'
                    'ACC_RollingCounter_30A'
                    'ACC_RollingCounter_30D'
                    'ACC_RollingCounter_367'
                )
                'GW_31A'
                7
                'ACC_CRCCheck_36D'
                8
                15
                'ACC_CRCCheck_30A'
                16
                23
                'ACC_CRCCheck_30D'
                24
                31
                'ACC_CRCCheck_367'
                '__pyarmor_exit_41420__'
            [Disassembly]
                0       NOP                             
                2       NOP                             
                4       PUSH_NULL                       
                6       LOAD_CONST                      2: '__pyarmor_enter_41419__'
                8       LOAD_CONST                      3: b'<COAddr>\x01\x00\x00\x1av\x01\x00\x00\x00\x00\x00\x00'
                10      BUILD_TUPLE                     1
                12      CALL_FUNCTION_EX                0
                14      POP_TOP                         
                16      RESUME                          0
                18      NOP                             
                20      NOP                             
                22      NOP                             
                24      NOP                             
                26      NOP                             
                28      LOAD_CONST                      4: ('ACC_CRCCheck_367', 'ACC_RollingCounter_367', 'ACC_LatPathHeadingAngle', 'ACC_LatPathDY', 'ACC_ELKEnableStatus', 'ACC_ELKInterventionMode', 'ACC_ELKMode', 'ACC_CRCCheck_30D', 'ACC_RollingCounter_30D', 'ACC_HighBeamControl', 'ACC_RRLaneDetection', 'ACC_LLLaneDetection', 'ACC_TargetBasedLateralControl', 'ACC_DriverHandsOffStatus', 'ACC_IACCHWATextInfoForDriver', 'ACC_IACCHWAMode', 'ACC_CRCCheck_30A', 'ACC_RollingCounter_30A', 'ACC_LaneChangeStatus', 'ACC_RoadCurvatureFar', 'ACC_RoadCurvatureNear', 'ACC_RoadCurvature', 'ACC_LLaneMarkerType', 'ACC_HostLaneLeftStatus', 'ACC_HostLaneRightStatus', 'ACC_IACCHWAEnable', 'ACC_RLaneMarkerType', 'ACC_CRCCheck_36D', 'ACC_RollingCounter_36D', 'ACC_FRadarFailureStatus', 'ACC_Voiceinfo', 'ACC_AEBTargetmode', 'ACC_AEBTextInfo', 'ACC_AEBStatus', 'ACC_ELKAlert', 'ACC_AEBTargetLatRange', 'ACC_AEBTargetRelSpeed', 'ACC_AEBTargetLngRange')
                30      GET_ITER                        
                32      LOAD_FAST_AND_CLEAR             6: _var_var_5
                34      SWAP                            2
                36      BUILD_MAP                       0
                38      SWAP                            2
                40      FOR_ITER                        8 (to 58)
                44      STORE_FAST                      6: _var_var_5
                46      LOAD_FAST                       6: _var_var_5
                48      LOAD_FAST                       1: msg
                50      LOAD_FAST                       6: _var_var_5
                52      BINARY_SUBSCR                   
                56      MAP_ADD                         2
                58      JUMP_BACKWARD                   10 (to 40)
                60      END_FOR                         
                62      STORE_FAST                      7: _var_var_3
                64      STORE_FAST                      6: _var_var_5
                66      LOAD_CONST                      5: 1
                68      STORE_FAST                      8: _var_var_6
                70      LOAD_FAST                       3: longActive
                72      POP_JUMP_IF_FALSE               7 (to 88)
                74      LOAD_FAST                       4: steeringPressed
                76      POP_JUMP_IF_FALSE               3 (to 84)
                78      LOAD_CONST                      6: 4
                80      STORE_FAST                      8: _var_var_6
                82      JUMP_FORWARD                    2 (to 88)
                84      LOAD_CONST                      7: 3
                86      STORE_FAST                      8: _var_var_6
                88      LOAD_FAST                       7: _var_var_3
                90      LOAD_ATTR                       1: update
                110     LOAD_FAST                       8: _var_var_6
                112     LOAD_FAST                       3: longActive
                114     POP_JUMP_IF_FALSE               4 (to 124)
                116     LOAD_FAST                       4: steeringPressed
                118     POP_JUMP_IF_TRUE                2 (to 124)
                120     LOAD_CONST                      8: 2
                122     JUMP_FORWARD                    1 (to 126)
                124     LOAD_CONST                      9: 0
                126     LOAD_CONST                      9: 0
                128     LOAD_CONST                      9: 0
                130     LOAD_CONST                      9: 0
                132     LOAD_FAST                       2: counter
                134     LOAD_FAST                       2: counter
                136     LOAD_FAST                       2: counter
                138     LOAD_FAST                       2: counter
                140     LOAD_CONST                      10: ('ACC_IACCHWAMode', 'ACC_TargetBasedLateralControl', 'ACC_AEBTextInfo', 'ACC_IACCHWATextInfoForDriver', 'ACC_ELKAlert', 'ACC_RollingCounter_36D', 'ACC_RollingCounter_30A', 'ACC_RollingCounter_30D', 'ACC_RollingCounter_367')
                142     BUILD_CONST_KEY_MAP             9
                144     CALL                            1
                152     POP_TOP                         
                154     LOAD_FAST                       0: packer
                156     LOAD_ATTR                       3: make_can_msg
                176     LOAD_CONST                      11: 'GW_31A'
                178     LOAD_CONST                      9: 0
                180     LOAD_FAST                       7: _var_var_3
                182     CALL                            3
                190     LOAD_CONST                      5: 1
                192     BINARY_SUBSCR                   
                196     STORE_FAST                      9: _var_var_4
                198     LOAD_GLOBAL                     5: NULL + crc_calculate_crc8
                208     LOAD_FAST                       9: _var_var_4
                210     LOAD_CONST                      0: None
                212     LOAD_CONST                      12: 7
                214     BINARY_SLICE                    
                216     CALL                            1
                224     LOAD_FAST                       7: _var_var_3
                226     LOAD_CONST                      13: 'ACC_CRCCheck_36D'
                228     STORE_SUBSCR                    
                232     LOAD_GLOBAL                     5: NULL + crc_calculate_crc8
                242     LOAD_FAST                       9: _var_var_4
                244     LOAD_CONST                      14: 8
                246     LOAD_CONST                      15: 15
                248     BINARY_SLICE                    
                250     CALL                            1
                258     LOAD_FAST                       7: _var_var_3
                260     LOAD_CONST                      16: 'ACC_CRCCheck_30A'
                262     STORE_SUBSCR                    
                266     LOAD_GLOBAL                     5: NULL + crc_calculate_crc8
                276     LOAD_FAST                       9: _var_var_4
                278     LOAD_CONST                      17: 16
                280     LOAD_CONST                      18: 23
                282     BINARY_SLICE                    
                284     CALL                            1
                292     LOAD_FAST                       7: _var_var_3
                294     LOAD_CONST                      19: 'ACC_CRCCheck_30D'
                296     STORE_SUBSCR                    
                300     LOAD_GLOBAL                     5: NULL + crc_calculate_crc8
                310     LOAD_FAST                       9: _var_var_4
                312     LOAD_CONST                      20: 24
                314     LOAD_CONST                      21: 31
                316     BINARY_SLICE                    
                318     CALL                            1
                326     LOAD_FAST                       7: _var_var_3
                328     LOAD_CONST                      22: 'ACC_CRCCheck_367'
                330     STORE_SUBSCR                    
                334     LOAD_FAST                       0: packer
                336     LOAD_ATTR                       3: make_can_msg
                356     LOAD_CONST                      11: 'GW_31A'
                358     LOAD_CONST                      9: 0
                360     LOAD_FAST                       7: _var_var_3
                362     CALL                            3
                370     NOP                             
                372     NOP                             
                374     NOP                             
                376     JUMP_FORWARD                    25 (to 428)
                378     CALL                            1
                386     POP_TOP                         
                388     RETURN_VALUE                    
                390     SWAP                            2
                392     POP_TOP                         
                394     SWAP                            2
                396     STORE_FAST                      6: _var_var_5
                398     RERAISE                         0
                400     PUSH_EXC_INFO                   
                402     PUSH_NULL                       
                404     LOAD_CONST                      23: '__pyarmor_exit_41420__'
                406     NOP                             
                408     LOAD_CONST                      3: b'<COAddr>\x01\x00\x00\x1av\x01\x00\x00\x00\x00\x00\x00'
                410     CALL                            1
                418     POP_TOP                         
                420     RERAISE                         0
                422     COPY                            3
                424     POP_EXCEPT                      
                426     RERAISE                         1
                428     PUSH_NULL                       
                430     LOAD_CONST                      23: '__pyarmor_exit_41420__'
                432     LOAD_CONST                      3: b'<COAddr>\x01\x00\x00\x1av\x01\x00\x00\x00\x00\x00\x00'
                434     BUILD_TUPLE                     1
                436     CALL_FUNCTION_EX                0
                438     POP_TOP                         
                440     RETURN_VALUE                    
            [Exception Table]
                28 to 36 -> 400 [0] 
                36 to 62 -> 390 [2] 
                62 to 370 -> 400 [0] 
                390 to 400 -> 400 [0] 
                400 to 422 -> 422 [1] lasti
        '__pyarmor_exit_41393__'
        None
        (
            4129
            65535
        )
    [Disassembly]
        0       NOP                             
        2       NOP                             
        4       PUSH_NULL                       
        6       LOAD_CONST                      1: '__pyarmor_enter_41392__'
        8       LOAD_CONST                      2: b'<COAddr>\x01\x00\x00\x1a\x82\x00\x00\x00\x00\x00\x00\x00'
        10      BUILD_TUPLE                     1
        12      CALL_FUNCTION_EX                0
        14      POP_TOP                         
        16      RESUME                          0
        18      NOP                             
        20      NOP                             
        22      NOP                             
        24      NOP                             
        26      BUILD_LIST                      0
        28      LOAD_CONST                      3: (0, 29, 58, 39, 116, 105, 78, 83, 232, 245, 210, 207, 156, 129, 166, 187, 205, 208, 247, 234, 185, 164, 131, 158, 37, 56, 31, 2, 81, 76, 107, 118, 135, 154, 189, 160, 243, 238, 201, 212, 111, 114, 85, 72, 27, 6, 33, 60, 74, 87, 112, 109, 62, 35, 4, 25, 162, 191, 152, 133, 214, 203, 236, 241, 19, 14, 41, 52, 103, 122, 93, 64, 251, 230, 193, 220, 143, 146, 181, 168, 222, 195, 228, 249, 170, 183, 144, 141, 54, 43, 12, 17, 66, 95, 120, 101, 148, 137, 174, 179, 224, 253, 218, 199, 124, 97, 70, 91, 8, 21, 50, 47, 89, 68, 99, 126, 45, 48, 23, 10, 177, 172, 139, 150, 197, 216, 255, 226, 38, 59, 28, 1, 82, 79, 104, 117, 206, 211, 244, 233, 186, 167, 128, 157, 235, 246, 209, 204, 159, 130, 165, 184, 3, 30, 57, 36, 119, 106, 77, 80, 161, 188, 155, 134, 213, 200, 239, 242, 73, 84, 115, 110, 61, 32, 7, 26, 108, 113, 86, 75, 24, 5, 34, 63, 132, 153, 190, 163, 240, 237, 202, 215, 53, 40, 15, 18, 65, 92, 123, 102, 221, 192, 231, 250, 169, 180, 147, 142, 248, 229, 194, 223, 140, 145, 182, 171, 16, 13, 42, 55, 100, 121, 94, 67, 178, 175, 136, 149, 198, 219, 252, 225, 90, 71, 96, 125, 46, 51, 20, 9, 127, 98, 69, 88, 11, 22, 49, 44, 151, 138, 173, 176, 227, 254, 217, 196)
        30      LIST_EXTEND                     1
        32      STORE_NAME                      1: crc8_tab
        34      LOAD_CONST                      4: <CODE> crc_calculate_crc8
        36      MAKE_FUNCTION                   0
        38      STORE_NAME                      2: crc_calculate_crc8
        40      LOAD_CONST                      18: (4129, 65535)
        42      LOAD_CONST                      5: 'data'
        44      LOAD_NAME                       3: bytes
        46      LOAD_CONST                      6: 'return'
        48      LOAD_NAME                       4: int
        50      BUILD_TUPLE                     4
        52      LOAD_CONST                      7: <CODE> crc16_ccitt_false
        54      MAKE_FUNCTION                   5
        56      STORE_NAME                      5: crc16_ccitt_false
        58      LOAD_CONST                      8: <CODE> create_244_command_a05
        60      MAKE_FUNCTION                   0
        62      STORE_NAME                      6: create_244_command_a05
        64      LOAD_CONST                      9: 'msg'
        66      LOAD_NAME                       7: dict
        68      BUILD_TUPLE                     2
        70      LOAD_CONST                      10: <CODE> create_244_command
        72      MAKE_FUNCTION                   4
        74      STORE_NAME                      8: create_244_command
        76      LOAD_CONST                      9: 'msg'
        78      LOAD_NAME                       7: dict
        80      BUILD_TUPLE                     2
        82      LOAD_CONST                      11: <CODE> create_244_command_idd
        84      MAKE_FUNCTION                   4
        86      STORE_NAME                      9: create_244_command_idd
        88      LOAD_CONST                      9: 'msg'
        90      LOAD_NAME                       7: dict
        92      BUILD_TUPLE                     2
        94      LOAD_CONST                      12: <CODE> create_1BA_command
        96      MAKE_FUNCTION                   4
        98      STORE_NAME                      10: create_1BA_command
        100     LOAD_CONST                      9: 'msg'
        102     LOAD_NAME                       7: dict
        104     BUILD_TUPLE                     2
        106     LOAD_CONST                      13: <CODE> create_17E_command
        108     MAKE_FUNCTION                   4
        110     STORE_NAME                      11: create_17E_command
        112     LOAD_CONST                      9: 'msg'
        114     LOAD_NAME                       7: dict
        116     BUILD_TUPLE                     2
        118     LOAD_CONST                      14: <CODE> create_307_command
        120     MAKE_FUNCTION                   4
        122     STORE_NAME                      12: create_307_command
        124     LOAD_CONST                      9: 'msg'
        126     LOAD_NAME                       7: dict
        128     BUILD_TUPLE                     2
        130     LOAD_CONST                      15: <CODE> create_31A_command
        132     MAKE_FUNCTION                   4
        134     STORE_NAME                      13: create_31A_command
        136     LOAD_CONST                      17: None
        138     NOP                             
        140     NOP                             
        142     NOP                             
        144     JUMP_FORWARD                    19 (to 184)
        152     POP_TOP                         
        154     RETURN_CONST                    17: None
        156     PUSH_EXC_INFO                   
        158     PUSH_NULL                       
        160     LOAD_CONST                      16: '__pyarmor_exit_41393__'
        162     NOP                             
        164     LOAD_CONST                      2: b'<COAddr>\x01\x00\x00\x1a\x82\x00\x00\x00\x00\x00\x00\x00'
        166     CALL                            1
        174     POP_TOP                         
        176     RERAISE                         0
        178     COPY                            3
        180     POP_EXCEPT                      
        182     RERAISE                         1
        184     PUSH_NULL                       
        186     LOAD_CONST                      16: '__pyarmor_exit_41393__'
        188     LOAD_CONST                      2: b'<COAddr>\x01\x00\x00\x1a\x82\x00\x00\x00\x00\x00\x00\x00'
        190     BUILD_TUPLE                     1
        192     CALL_FUNCTION_EX                0
        194     POP_TOP                         
        196     RETURN_VALUE                    
    [Exception Table]
        26 to 136 -> 156 [0] 
        156 to 178 -> 178 [1] lasti
